{"fips":"1053","state":"AL","county":"Escambia","tier":"amber","quotable":true,"n_events_total":5366,"observation_years":11.16723705,"mcc":18593.0,"rows_policy":"top_200_longest_events","rows_returned":200,"threshold_summary":{"2":{"qualifying_events":1962,"S_T":0.36563548,"lambda_T":175.69251829},"4":{"qualifying_events":778,"S_T":0.14498695,"lambda_T":69.66808319},"8":{"qualifying_events":194,"S_T":0.03615356,"lambda_T":17.37224697},"12":{"qualifying_events":74,"S_T":0.01379053,"lambda_T":6.62652719},"24":{"qualifying_events":16,"S_T":0.00298174,"lambda_T":1.43276264}},"events":[{"rank_by_duration":1,"event_id":"1053_20200915T224500","start_time_utc":"2020-09-15T22:45:00","end_time_utc":"2020-09-25T12:00:00","year":2020,"duration_hours":229.25,"n_snapshots":917,"min_customers_out":4,"max_customers_out":9643,"mean_customers_out":1680.34,"peak_out_pct_mcc":0.518636},{"rank_by_duration":2,"event_id":"1053_20201029T020000","start_time_utc":"2020-10-29T02:00:00","end_time_utc":"2020-11-01T20:30:00","year":2020,"duration_hours":90.5,"n_snapshots":352,"min_customers_out":4,"max_customers_out":6027,"mean_customers_out":1406.73,"peak_out_pct_mcc":0.324154},{"rank_by_duration":3,"event_id":"1053_20240905T071500","start_time_utc":"2024-09-05T07:15:00","end_time_utc":"2024-09-08T16:45:00","year":2024,"duration_hours":81.5,"n_snapshots":326,"min_customers_out":15,"max_customers_out":274,"mean_customers_out":18.945,"peak_out_pct_mcc":0.014737},{"rank_by_duration":4,"event_id":"1053_20251003T204500","start_time_utc":"2025-10-03T20:45:00","end_time_utc":"2025-10-06T12:45:00","year":2025,"duration_hours":64.0,"n_snapshots":256,"min_customers_out":4,"max_customers_out":99,"mean_customers_out":7.188,"peak_out_pct_mcc":0.005325},{"rank_by_duration":5,"event_id":"1053_20230616T113000","start_time_utc":"2023-06-16T11:30:00","end_time_utc":"2023-06-19T00:00:00","year":2023,"duration_hours":60.5,"n_snapshots":240,"min_customers_out":4,"max_customers_out":6245,"mean_customers_out":724.283,"peak_out_pct_mcc":0.335879},{"rank_by_duration":6,"event_id":"1053_20210619T021500","start_time_utc":"2021-06-19T02:15:00","end_time_utc":"2021-06-21T03:45:00","year":2021,"duration_hours":49.5,"n_snapshots":196,"min_customers_out":4,"max_customers_out":1486,"mean_customers_out":526.051,"peak_out_pct_mcc":0.079923},{"rank_by_duration":7,"event_id":"1053_20231106T200000","start_time_utc":"2023-11-06T20:00:00","end_time_utc":"2023-11-08T19:45:00","year":2023,"duration_hours":47.75,"n_snapshots":189,"min_customers_out":4,"max_customers_out":14,"mean_customers_out":4.429,"peak_out_pct_mcc":0.000753},{"rank_by_duration":8,"event_id":"1053_20200421T060000","start_time_utc":"2020-04-21T06:00:00","end_time_utc":"2020-04-23T01:15:00","year":2020,"duration_hours":43.25,"n_snapshots":173,"min_customers_out":2,"max_customers_out":13,"mean_customers_out":2.497,"peak_out_pct_mcc":0.000699},{"rank_by_duration":9,"event_id":"1053_20240109T044500","start_time_utc":"2024-01-09T04:45:00","end_time_utc":"2024-01-10T22:45:00","year":2024,"duration_hours":42.0,"n_snapshots":168,"min_customers_out":4,"max_customers_out":893,"mean_customers_out":153.101,"peak_out_pct_mcc":0.048029},{"rank_by_duration":10,"event_id":"1053_20190714T011500","start_time_utc":"2019-07-14T01:15:00","end_time_utc":"2019-07-15T13:45:00","year":2019,"duration_hours":36.5,"n_snapshots":146,"min_customers_out":4,"max_customers_out":4,"mean_customers_out":4.0,"peak_out_pct_mcc":0.000215},{"rank_by_duration":11,"event_id":"1053_20240513T121500","start_time_utc":"2024-05-13T12:15:00","end_time_utc":"2024-05-14T21:45:00","year":2024,"duration_hours":33.5,"n_snapshots":134,"min_customers_out":4,"max_customers_out":1013,"mean_customers_out":232.836,"peak_out_pct_mcc":0.054483},{"rank_by_duration":12,"event_id":"1053_20211006T134500","start_time_utc":"2021-10-06T13:45:00","end_time_utc":"2021-10-07T20:15:00","year":2021,"duration_hours":30.5,"n_snapshots":120,"min_customers_out":4,"max_customers_out":71,"mean_customers_out":9.658,"peak_out_pct_mcc":0.003819},{"rank_by_duration":13,"event_id":"1053_20210424T103000","start_time_utc":"2021-04-24T10:30:00","end_time_utc":"2021-04-25T16:15:00","year":2021,"duration_hours":29.75,"n_snapshots":119,"min_customers_out":4,"max_customers_out":3523,"mean_customers_out":579.193,"peak_out_pct_mcc":0.18948},{"rank_by_duration":14,"event_id":"1053_20240510T084500","start_time_utc":"2024-05-10T08:45:00","end_time_utc":"2024-05-11T13:45:00","year":2024,"duration_hours":29.0,"n_snapshots":114,"min_customers_out":4,"max_customers_out":344,"mean_customers_out":73.798,"peak_out_pct_mcc":0.018502},{"rank_by_duration":15,"event_id":"1053_20250406T220000","start_time_utc":"2025-04-06T22:00:00","end_time_utc":"2025-04-08T00:45:00","year":2025,"duration_hours":26.75,"n_snapshots":107,"min_customers_out":4,"max_customers_out":259,"mean_customers_out":70.607,"peak_out_pct_mcc":0.01393},{"rank_by_duration":16,"event_id":"1053_20221215T010000","start_time_utc":"2022-12-15T01:00:00","end_time_utc":"2022-12-16T01:15:00","year":2022,"duration_hours":24.25,"n_snapshots":92,"min_customers_out":4,"max_customers_out":316,"mean_customers_out":34.315,"peak_out_pct_mcc":0.016996},{"rank_by_duration":17,"event_id":"1053_20220925T123000","start_time_utc":"2022-09-25T12:30:00","end_time_utc":"2022-09-26T11:15:00","year":2022,"duration_hours":22.75,"n_snapshots":91,"min_customers_out":4,"max_customers_out":4,"mean_customers_out":4.0,"peak_out_pct_mcc":0.000215},{"rank_by_duration":18,"event_id":"1053_20210728T220000","start_time_utc":"2021-07-28T22:00:00","end_time_utc":"2021-07-29T19:45:00","year":2021,"duration_hours":21.75,"n_snapshots":85,"min_customers_out":4,"max_customers_out":31,"mean_customers_out":6.729,"peak_out_pct_mcc":0.001667},{"rank_by_duration":19,"event_id":"1053_20221231T194500","start_time_utc":"2022-12-31T19:45:00","end_time_utc":"2023-01-01T17:15:00","year":2022,"duration_hours":21.5,"n_snapshots":86,"min_customers_out":4,"max_customers_out":4,"mean_customers_out":4.0,"peak_out_pct_mcc":0.000215},{"rank_by_duration":20,"event_id":"1053_20180628T233000","start_time_utc":"2018-06-28T23:30:00","end_time_utc":"2018-06-29T20:45:00","year":2018,"duration_hours":21.25,"n_snapshots":85,"min_customers_out":4,"max_customers_out":3368,"mean_customers_out":409.624,"peak_out_pct_mcc":0.181143},{"rank_by_duration":21,"event_id":"1053_20250304T204500","start_time_utc":"2025-03-04T20:45:00","end_time_utc":"2025-03-05T17:30:00","year":2025,"duration_hours":20.75,"n_snapshots":83,"min_customers_out":4,"max_customers_out":1618,"mean_customers_out":243.133,"peak_out_pct_mcc":0.087022},{"rank_by_duration":22,"event_id":"1053_20180726T150000","start_time_utc":"2018-07-26T15:00:00","end_time_utc":"2018-07-27T11:30:00","year":2018,"duration_hours":20.5,"n_snapshots":82,"min_customers_out":4,"max_customers_out":7,"mean_customers_out":4.183,"peak_out_pct_mcc":0.000376},{"rank_by_duration":23,"event_id":"1053_20250919T224500","start_time_utc":"2025-09-19T22:45:00","end_time_utc":"2025-09-20T18:00:00","year":2025,"duration_hours":19.25,"n_snapshots":76,"min_customers_out":4,"max_customers_out":56,"mean_customers_out":7.789,"peak_out_pct_mcc":0.003012},{"rank_by_duration":24,"event_id":"1053_20200126T173000","start_time_utc":"2020-01-26T17:30:00","end_time_utc":"2020-01-27T12:15:00","year":2020,"duration_hours":18.75,"n_snapshots":75,"min_customers_out":4,"max_customers_out":4,"mean_customers_out":4.0,"peak_out_pct_mcc":0.000215},{"rank_by_duration":25,"event_id":"1053_20220727T200000","start_time_utc":"2022-07-27T20:00:00","end_time_utc":"2022-07-28T14:30:00","year":2022,"duration_hours":18.5,"n_snapshots":74,"min_customers_out":4,"max_customers_out":4,"mean_customers_out":4.0,"peak_out_pct_mcc":0.000215},{"rank_by_duration":26,"event_id":"1053_20180114T221500","start_time_utc":"2018-01-14T22:15:00","end_time_utc":"2018-01-15T16:30:00","year":2018,"duration_hours":18.25,"n_snapshots":73,"min_customers_out":1,"max_customers_out":9,"mean_customers_out":1.836,"peak_out_pct_mcc":0.000484},{"rank_by_duration":27,"event_id":"1053_20220830T133000","start_time_utc":"2022-08-30T13:30:00","end_time_utc":"2022-08-31T06:30:00","year":2022,"duration_hours":17.0,"n_snapshots":65,"min_customers_out":4,"max_customers_out":1093,"mean_customers_out":186.585,"peak_out_pct_mcc":0.058786},{"rank_by_duration":28,"event_id":"1053_20210831T004500","start_time_utc":"2021-08-31T00:45:00","end_time_utc":"2021-08-31T17:45:00","year":2021,"duration_hours":17.0,"n_snapshots":67,"min_customers_out":4,"max_customers_out":179,"mean_customers_out":30.522,"peak_out_pct_mcc":0.009627},{"rank_by_duration":29,"event_id":"1053_20240914T104500","start_time_utc":"2024-09-14T10:45:00","end_time_utc":"2024-09-15T03:30:00","year":2024,"duration_hours":16.75,"n_snapshots":65,"min_customers_out":4,"max_customers_out":14,"mean_customers_out":9.846,"peak_out_pct_mcc":0.000753},{"rank_by_duration":30,"event_id":"1053_20230619T091500","start_time_utc":"2023-06-19T09:15:00","end_time_utc":"2023-06-20T01:30:00","year":2023,"duration_hours":16.25,"n_snapshots":63,"min_customers_out":4,"max_customers_out":328,"mean_customers_out":31.048,"peak_out_pct_mcc":0.017641},{"rank_by_duration":31,"event_id":"1053_20200708T003000","start_time_utc":"2020-07-08T00:30:00","end_time_utc":"2020-07-08T16:45:00","year":2020,"duration_hours":16.25,"n_snapshots":65,"min_customers_out":4,"max_customers_out":4,"mean_customers_out":4.0,"peak_out_pct_mcc":0.000215},{"rank_by_duration":32,"event_id":"1053_20190419T051500","start_time_utc":"2019-04-19T05:15:00","end_time_utc":"2019-04-19T21:15:00","year":2019,"duration_hours":16.0,"n_snapshots":64,"min_customers_out":2,"max_customers_out":387,"mean_customers_out":67.891,"peak_out_pct_mcc":0.020814},{"rank_by_duration":33,"event_id":"1053_20220704T090000","start_time_utc":"2022-07-04T09:00:00","end_time_utc":"2022-07-05T01:00:00","year":2022,"duration_hours":16.0,"n_snapshots":62,"min_customers_out":4,"max_customers_out":380,"mean_customers_out":72.613,"peak_out_pct_mcc":0.020438},{"rank_by_duration":34,"event_id":"1053_20220208T034500","start_time_utc":"2022-02-08T03:45:00","end_time_utc":"2022-02-08T19:15:00","year":2022,"duration_hours":15.5,"n_snapshots":62,"min_customers_out":4,"max_customers_out":4,"mean_customers_out":4.0,"peak_out_pct_mcc":0.000215},{"rank_by_duration":35,"event_id":"1053_20190809T220000","start_time_utc":"2019-08-09T22:00:00","end_time_utc":"2019-08-10T13:15:00","year":2019,"duration_hours":15.25,"n_snapshots":61,"min_customers_out":4,"max_customers_out":684,"mean_customers_out":31.213,"peak_out_pct_mcc":0.036788},{"rank_by_duration":36,"event_id":"1053_20240525T053000","start_time_utc":"2024-05-25T05:30:00","end_time_utc":"2024-05-25T20:30:00","year":2024,"duration_hours":15.0,"n_snapshots":60,"min_customers_out":4,"max_customers_out":16,"mean_customers_out":10.183,"peak_out_pct_mcc":0.000861},{"rank_by_duration":37,"event_id":"1053_20250216T083000","start_time_utc":"2025-02-16T08:30:00","end_time_utc":"2025-02-16T23:15:00","year":2025,"duration_hours":14.75,"n_snapshots":59,"min_customers_out":4,"max_customers_out":1071,"mean_customers_out":246.492,"peak_out_pct_mcc":0.057602},{"rank_by_duration":38,"event_id":"1053_20210813T021500","start_time_utc":"2021-08-13T02:15:00","end_time_utc":"2021-08-13T17:00:00","year":2021,"duration_hours":14.75,"n_snapshots":59,"min_customers_out":4,"max_customers_out":6,"mean_customers_out":4.441,"peak_out_pct_mcc":0.000323},{"rank_by_duration":39,"event_id":"1053_20241014T061500","start_time_utc":"2024-10-14T06:15:00","end_time_utc":"2024-10-14T20:45:00","year":2024,"duration_hours":14.5,"n_snapshots":58,"min_customers_out":4,"max_customers_out":8,"mean_customers_out":4.259,"peak_out_pct_mcc":0.00043},{"rank_by_duration":40,"event_id":"1053_20250123T031500","start_time_utc":"2025-01-23T03:15:00","end_time_utc":"2025-01-23T17:45:00","year":2025,"duration_hours":14.5,"n_snapshots":57,"min_customers_out":4,"max_customers_out":6,"mean_customers_out":4.105,"peak_out_pct_mcc":0.000323},{"rank_by_duration":41,"event_id":"1053_20171126T180000","start_time_utc":"2017-11-26T18:00:00","end_time_utc":"2017-11-27T08:30:00","year":2017,"duration_hours":14.5,"n_snapshots":58,"min_customers_out":1,"max_customers_out":2,"mean_customers_out":1.086,"peak_out_pct_mcc":0.000108},{"rank_by_duration":42,"event_id":"1053_20200304T141500","start_time_utc":"2020-03-04T14:15:00","end_time_utc":"2020-03-05T04:30:00","year":2020,"duration_hours":14.25,"n_snapshots":57,"min_customers_out":4,"max_customers_out":1743,"mean_customers_out":856.298,"peak_out_pct_mcc":0.093745},{"rank_by_duration":43,"event_id":"1053_20240101T154500","start_time_utc":"2024-01-01T15:45:00","end_time_utc":"2024-01-02T06:00:00","year":2024,"duration_hours":14.25,"n_snapshots":55,"min_customers_out":4,"max_customers_out":7,"mean_customers_out":4.164,"peak_out_pct_mcc":0.000376},{"rank_by_duration":44,"event_id":"1053_20240119T034500","start_time_utc":"2024-01-19T03:45:00","end_time_utc":"2024-01-19T17:45:00","year":2024,"duration_hours":14.0,"n_snapshots":53,"min_customers_out":4,"max_customers_out":4,"mean_customers_out":4.0,"peak_out_pct_mcc":0.000215},{"rank_by_duration":45,"event_id":"1053_20230125T061500","start_time_utc":"2023-01-25T06:15:00","end_time_utc":"2023-01-25T20:00:00","year":2023,"duration_hours":13.75,"n_snapshots":55,"min_customers_out":4,"max_customers_out":214,"mean_customers_out":78.8,"peak_out_pct_mcc":0.01151},{"rank_by_duration":46,"event_id":"1053_20200703T214500","start_time_utc":"2020-07-03T21:45:00","end_time_utc":"2020-07-04T11:30:00","year":2020,"duration_hours":13.75,"n_snapshots":55,"min_customers_out":4,"max_customers_out":61,"mean_customers_out":11.764,"peak_out_pct_mcc":0.003281},{"rank_by_duration":47,"event_id":"1053_20250722T221500","start_time_utc":"2025-07-22T22:15:00","end_time_utc":"2025-07-23T12:00:00","year":2025,"duration_hours":13.75,"n_snapshots":55,"min_customers_out":4,"max_customers_out":4,"mean_customers_out":4.0,"peak_out_pct_mcc":0.000215},{"rank_by_duration":48,"event_id":"1053_20211107T140000","start_time_utc":"2021-11-07T14:00:00","end_time_utc":"2021-11-08T03:30:00","year":2021,"duration_hours":13.5,"n_snapshots":54,"min_customers_out":4,"max_customers_out":47,"mean_customers_out":11.963,"peak_out_pct_mcc":0.002528},{"rank_by_duration":49,"event_id":"1053_20250620T171500","start_time_utc":"2025-06-20T17:15:00","end_time_utc":"2025-06-21T06:45:00","year":2025,"duration_hours":13.5,"n_snapshots":52,"min_customers_out":4,"max_customers_out":39,"mean_customers_out":6.962,"peak_out_pct_mcc":0.002098},{"rank_by_duration":50,"event_id":"1053_20180517T123000","start_time_utc":"2018-05-17T12:30:00","end_time_utc":"2018-05-18T01:45:00","year":2018,"duration_hours":13.25,"n_snapshots":53,"min_customers_out":4,"max_customers_out":444,"mean_customers_out":68.623,"peak_out_pct_mcc":0.02388},{"rank_by_duration":51,"event_id":"1053_20250609T001500","start_time_utc":"2025-06-09T00:15:00","end_time_utc":"2025-06-09T13:30:00","year":2025,"duration_hours":13.25,"n_snapshots":52,"min_customers_out":4,"max_customers_out":107,"mean_customers_out":44.731,"peak_out_pct_mcc":0.005755},{"rank_by_duration":52,"event_id":"1053_20230112T170000","start_time_utc":"2023-01-12T17:00:00","end_time_utc":"2023-01-13T06:00:00","year":2023,"duration_hours":13.0,"n_snapshots":52,"min_customers_out":4,"max_customers_out":151,"mean_customers_out":50.462,"peak_out_pct_mcc":0.008121},{"rank_by_duration":53,"event_id":"1053_20250616T171500","start_time_utc":"2025-06-16T17:15:00","end_time_utc":"2025-06-17T06:15:00","year":2025,"duration_hours":13.0,"n_snapshots":51,"min_customers_out":4,"max_customers_out":75,"mean_customers_out":13.353,"peak_out_pct_mcc":0.004034},{"rank_by_duration":54,"event_id":"1053_20210807T051500","start_time_utc":"2021-08-07T05:15:00","end_time_utc":"2021-08-07T18:15:00","year":2021,"duration_hours":13.0,"n_snapshots":52,"min_customers_out":4,"max_customers_out":4,"mean_customers_out":4.0,"peak_out_pct_mcc":0.000215},{"rank_by_duration":55,"event_id":"1053_20210517T214500","start_time_utc":"2021-05-17T21:45:00","end_time_utc":"2021-05-18T10:45:00","year":2021,"duration_hours":13.0,"n_snapshots":52,"min_customers_out":4,"max_customers_out":4,"mean_customers_out":4.0,"peak_out_pct_mcc":0.000215},{"rank_by_duration":56,"event_id":"1053_20171213T023000","start_time_utc":"2017-12-13T02:30:00","end_time_utc":"2017-12-13T15:30:00","year":2017,"duration_hours":13.0,"n_snapshots":51,"min_customers_out":1,"max_customers_out":1,"mean_customers_out":1.0,"peak_out_pct_mcc":5.4e-05},{"rank_by_duration":57,"event_id":"1053_20180818T141500","start_time_utc":"2018-08-18T14:15:00","end_time_utc":"2018-08-19T03:00:00","year":2018,"duration_hours":12.75,"n_snapshots":51,"min_customers_out":4,"max_customers_out":703,"mean_customers_out":42.882,"peak_out_pct_mcc":0.03781},{"rank_by_duration":58,"event_id":"1053_20210721T030000","start_time_utc":"2021-07-21T03:00:00","end_time_utc":"2021-07-21T15:45:00","year":2021,"duration_hours":12.75,"n_snapshots":51,"min_customers_out":4,"max_customers_out":23,"mean_customers_out":4.373,"peak_out_pct_mcc":0.001237},{"rank_by_duration":59,"event_id":"1053_20180623T024500","start_time_utc":"2018-06-23T02:45:00","end_time_utc":"2018-06-23T15:30:00","year":2018,"duration_hours":12.75,"n_snapshots":51,"min_customers_out":4,"max_customers_out":17,"mean_customers_out":5.529,"peak_out_pct_mcc":0.000914},{"rank_by_duration":60,"event_id":"1053_20241210T094500","start_time_utc":"2024-12-10T09:45:00","end_time_utc":"2024-12-10T22:30:00","year":2024,"duration_hours":12.75,"n_snapshots":47,"min_customers_out":4,"max_customers_out":8,"mean_customers_out":4.511,"peak_out_pct_mcc":0.00043},{"rank_by_duration":61,"event_id":"1053_20250223T143000","start_time_utc":"2025-02-23T14:30:00","end_time_utc":"2025-02-24T03:15:00","year":2025,"duration_hours":12.75,"n_snapshots":51,"min_customers_out":4,"max_customers_out":4,"mean_customers_out":4.0,"peak_out_pct_mcc":0.000215},{"rank_by_duration":62,"event_id":"1053_20210322T033000","start_time_utc":"2021-03-22T03:30:00","end_time_utc":"2021-03-22T16:15:00","year":2021,"duration_hours":12.75,"n_snapshots":51,"min_customers_out":4,"max_customers_out":4,"mean_customers_out":4.0,"peak_out_pct_mcc":0.000215},{"rank_by_duration":63,"event_id":"1053_20210410T084500","start_time_utc":"2021-04-10T08:45:00","end_time_utc":"2021-04-10T21:15:00","year":2021,"duration_hours":12.5,"n_snapshots":50,"min_customers_out":4,"max_customers_out":342,"mean_customers_out":47.44,"peak_out_pct_mcc":0.018394},{"rank_by_duration":64,"event_id":"1053_20200210T041500","start_time_utc":"2020-02-10T04:15:00","end_time_utc":"2020-02-10T16:45:00","year":2020,"duration_hours":12.5,"n_snapshots":48,"min_customers_out":4,"max_customers_out":57,"mean_customers_out":6.188,"peak_out_pct_mcc":0.003066},{"rank_by_duration":65,"event_id":"1053_20200423T130000","start_time_utc":"2020-04-23T13:00:00","end_time_utc":"2020-04-24T01:15:00","year":2020,"duration_hours":12.25,"n_snapshots":48,"min_customers_out":4,"max_customers_out":3898,"mean_customers_out":1678.708,"peak_out_pct_mcc":0.209649},{"rank_by_duration":66,"event_id":"1053_20241120T143000","start_time_utc":"2024-11-20T14:30:00","end_time_utc":"2024-11-21T02:45:00","year":2024,"duration_hours":12.25,"n_snapshots":49,"min_customers_out":4,"max_customers_out":287,"mean_customers_out":57.898,"peak_out_pct_mcc":0.015436},{"rank_by_duration":67,"event_id":"1053_20230615T194500","start_time_utc":"2023-06-15T19:45:00","end_time_utc":"2023-06-16T08:00:00","year":2023,"duration_hours":12.25,"n_snapshots":45,"min_customers_out":4,"max_customers_out":264,"mean_customers_out":122.511,"peak_out_pct_mcc":0.014199},{"rank_by_duration":68,"event_id":"1053_20180417T130000","start_time_utc":"2018-04-17T13:00:00","end_time_utc":"2018-04-18T01:15:00","year":2018,"duration_hours":12.25,"n_snapshots":49,"min_customers_out":4,"max_customers_out":78,"mean_customers_out":12.327,"peak_out_pct_mcc":0.004195},{"rank_by_duration":69,"event_id":"1053_20250114T134500","start_time_utc":"2025-01-14T13:45:00","end_time_utc":"2025-01-15T02:00:00","year":2025,"duration_hours":12.25,"n_snapshots":48,"min_customers_out":4,"max_customers_out":12,"mean_customers_out":7.438,"peak_out_pct_mcc":0.000645},{"rank_by_duration":70,"event_id":"1053_20221120T011500","start_time_utc":"2022-11-20T01:15:00","end_time_utc":"2022-11-20T13:30:00","year":2022,"duration_hours":12.25,"n_snapshots":49,"min_customers_out":4,"max_customers_out":7,"mean_customers_out":5.163,"peak_out_pct_mcc":0.000376},{"rank_by_duration":71,"event_id":"1053_20250314T041500","start_time_utc":"2025-03-14T04:15:00","end_time_utc":"2025-03-14T16:30:00","year":2025,"duration_hours":12.25,"n_snapshots":47,"min_customers_out":4,"max_customers_out":4,"mean_customers_out":4.0,"peak_out_pct_mcc":0.000215},{"rank_by_duration":72,"event_id":"1053_20200420T031500","start_time_utc":"2020-04-20T03:15:00","end_time_utc":"2020-04-20T15:15:00","year":2020,"duration_hours":12.0,"n_snapshots":46,"min_customers_out":4,"max_customers_out":199,"mean_customers_out":97.63,"peak_out_pct_mcc":0.010703},{"rank_by_duration":73,"event_id":"1053_20240717T123000","start_time_utc":"2024-07-17T12:30:00","end_time_utc":"2024-07-18T00:30:00","year":2024,"duration_hours":12.0,"n_snapshots":48,"min_customers_out":4,"max_customers_out":32,"mean_customers_out":7.667,"peak_out_pct_mcc":0.001721},{"rank_by_duration":74,"event_id":"1053_20210801T031500","start_time_utc":"2021-08-01T03:15:00","end_time_utc":"2021-08-01T15:15:00","year":2021,"duration_hours":12.0,"n_snapshots":48,"min_customers_out":4,"max_customers_out":4,"mean_customers_out":4.0,"peak_out_pct_mcc":0.000215},{"rank_by_duration":75,"event_id":"1053_20220318T130000","start_time_utc":"2022-03-18T13:00:00","end_time_utc":"2022-03-19T00:45:00","year":2022,"duration_hours":11.75,"n_snapshots":47,"min_customers_out":4,"max_customers_out":811,"mean_customers_out":187.128,"peak_out_pct_mcc":0.043619},{"rank_by_duration":76,"event_id":"1053_20191027T044500","start_time_utc":"2019-10-27T04:45:00","end_time_utc":"2019-10-27T16:30:00","year":2019,"duration_hours":11.75,"n_snapshots":45,"min_customers_out":4,"max_customers_out":73,"mean_customers_out":9.756,"peak_out_pct_mcc":0.003926},{"rank_by_duration":77,"event_id":"1053_20180905T043000","start_time_utc":"2018-09-05T04:30:00","end_time_utc":"2018-09-05T16:15:00","year":2018,"duration_hours":11.75,"n_snapshots":46,"min_customers_out":4,"max_customers_out":6,"mean_customers_out":5.326,"peak_out_pct_mcc":0.000323},{"rank_by_duration":78,"event_id":"1053_20220728T160000","start_time_utc":"2022-07-28T16:00:00","end_time_utc":"2022-07-29T03:45:00","year":2022,"duration_hours":11.75,"n_snapshots":47,"min_customers_out":4,"max_customers_out":4,"mean_customers_out":4.0,"peak_out_pct_mcc":0.000215},{"rank_by_duration":79,"event_id":"1053_20250715T053000","start_time_utc":"2025-07-15T05:30:00","end_time_utc":"2025-07-15T17:00:00","year":2025,"duration_hours":11.5,"n_snapshots":46,"min_customers_out":4,"max_customers_out":75,"mean_customers_out":14.783,"peak_out_pct_mcc":0.004034},{"rank_by_duration":80,"event_id":"1053_20220709T204500","start_time_utc":"2022-07-09T20:45:00","end_time_utc":"2022-07-10T08:15:00","year":2022,"duration_hours":11.5,"n_snapshots":45,"min_customers_out":4,"max_customers_out":24,"mean_customers_out":10.444,"peak_out_pct_mcc":0.001291},{"rank_by_duration":81,"event_id":"1053_20200305T123000","start_time_utc":"2020-03-05T12:30:00","end_time_utc":"2020-03-06T00:00:00","year":2020,"duration_hours":11.5,"n_snapshots":45,"min_customers_out":4,"max_customers_out":7,"mean_customers_out":4.378,"peak_out_pct_mcc":0.000376},{"rank_by_duration":82,"event_id":"1053_20210121T041500","start_time_utc":"2021-01-21T04:15:00","end_time_utc":"2021-01-21T15:45:00","year":2021,"duration_hours":11.5,"n_snapshots":44,"min_customers_out":4,"max_customers_out":4,"mean_customers_out":4.0,"peak_out_pct_mcc":0.000215},{"rank_by_duration":83,"event_id":"1053_20190602T080000","start_time_utc":"2019-06-02T08:00:00","end_time_utc":"2019-06-02T19:15:00","year":2019,"duration_hours":11.25,"n_snapshots":45,"min_customers_out":4,"max_customers_out":9,"mean_customers_out":4.778,"peak_out_pct_mcc":0.000484},{"rank_by_duration":84,"event_id":"1053_20230621T030000","start_time_utc":"2023-06-21T03:00:00","end_time_utc":"2023-06-21T14:15:00","year":2023,"duration_hours":11.25,"n_snapshots":45,"min_customers_out":4,"max_customers_out":4,"mean_customers_out":4.0,"peak_out_pct_mcc":0.000215},{"rank_by_duration":85,"event_id":"1053_20230612T224500","start_time_utc":"2023-06-12T22:45:00","end_time_utc":"2023-06-13T09:45:00","year":2023,"duration_hours":11.0,"n_snapshots":44,"min_customers_out":4,"max_customers_out":412,"mean_customers_out":77.955,"peak_out_pct_mcc":0.022159},{"rank_by_duration":86,"event_id":"1053_20211005T141500","start_time_utc":"2021-10-05T14:15:00","end_time_utc":"2021-10-06T01:15:00","year":2021,"duration_hours":11.0,"n_snapshots":42,"min_customers_out":4,"max_customers_out":95,"mean_customers_out":15.357,"peak_out_pct_mcc":0.005109},{"rank_by_duration":87,"event_id":"1053_20241229T111500","start_time_utc":"2024-12-29T11:15:00","end_time_utc":"2024-12-29T22:15:00","year":2024,"duration_hours":11.0,"n_snapshots":44,"min_customers_out":4,"max_customers_out":6,"mean_customers_out":4.545,"peak_out_pct_mcc":0.000323},{"rank_by_duration":88,"event_id":"1053_20231115T111500","start_time_utc":"2023-11-15T11:15:00","end_time_utc":"2023-11-15T22:15:00","year":2023,"duration_hours":11.0,"n_snapshots":43,"min_customers_out":4,"max_customers_out":4,"mean_customers_out":4.0,"peak_out_pct_mcc":0.000215},{"rank_by_duration":89,"event_id":"1053_20250609T211500","start_time_utc":"2025-06-09T21:15:00","end_time_utc":"2025-06-10T08:00:00","year":2025,"duration_hours":10.75,"n_snapshots":42,"min_customers_out":4,"max_customers_out":513,"mean_customers_out":121.429,"peak_out_pct_mcc":0.027591},{"rank_by_duration":90,"event_id":"1053_20190721T190000","start_time_utc":"2019-07-21T19:00:00","end_time_utc":"2019-07-22T05:45:00","year":2019,"duration_hours":10.75,"n_snapshots":43,"min_customers_out":13,"max_customers_out":31,"mean_customers_out":21.791,"peak_out_pct_mcc":0.001667},{"rank_by_duration":91,"event_id":"1053_20180414T133000","start_time_utc":"2018-04-14T13:30:00","end_time_utc":"2018-04-15T00:15:00","year":2018,"duration_hours":10.75,"n_snapshots":43,"min_customers_out":4,"max_customers_out":20,"mean_customers_out":7.116,"peak_out_pct_mcc":0.001076},{"rank_by_duration":92,"event_id":"1053_20250122T004500","start_time_utc":"2025-01-22T00:45:00","end_time_utc":"2025-01-22T11:15:00","year":2025,"duration_hours":10.5,"n_snapshots":42,"min_customers_out":4,"max_customers_out":1032,"mean_customers_out":343.571,"peak_out_pct_mcc":0.055505},{"rank_by_duration":93,"event_id":"1053_20250815T221500","start_time_utc":"2025-08-15T22:15:00","end_time_utc":"2025-08-16T08:45:00","year":2025,"duration_hours":10.5,"n_snapshots":42,"min_customers_out":4,"max_customers_out":131,"mean_customers_out":38.667,"peak_out_pct_mcc":0.007046},{"rank_by_duration":94,"event_id":"1053_20180301T134500","start_time_utc":"2018-03-01T13:45:00","end_time_utc":"2018-03-02T00:15:00","year":2018,"duration_hours":10.5,"n_snapshots":38,"min_customers_out":4,"max_customers_out":74,"mean_customers_out":14.711,"peak_out_pct_mcc":0.00398},{"rank_by_duration":95,"event_id":"1053_20230413T110000","start_time_utc":"2023-04-13T11:00:00","end_time_utc":"2023-04-13T21:30:00","year":2023,"duration_hours":10.5,"n_snapshots":42,"min_customers_out":4,"max_customers_out":42,"mean_customers_out":20.119,"peak_out_pct_mcc":0.002259},{"rank_by_duration":96,"event_id":"1053_20200813T190000","start_time_utc":"2020-08-13T19:00:00","end_time_utc":"2020-08-14T05:30:00","year":2020,"duration_hours":10.5,"n_snapshots":38,"min_customers_out":4,"max_customers_out":24,"mean_customers_out":6.947,"peak_out_pct_mcc":0.001291},{"rank_by_duration":97,"event_id":"1053_20180113T170000","start_time_utc":"2018-01-13T17:00:00","end_time_utc":"2018-01-14T03:30:00","year":2018,"duration_hours":10.5,"n_snapshots":42,"min_customers_out":1,"max_customers_out":1,"mean_customers_out":1.0,"peak_out_pct_mcc":5.4e-05},{"rank_by_duration":98,"event_id":"1053_20240325T150000","start_time_utc":"2024-03-25T15:00:00","end_time_utc":"2024-03-26T01:15:00","year":2024,"duration_hours":10.25,"n_snapshots":41,"min_customers_out":4,"max_customers_out":9,"mean_customers_out":4.268,"peak_out_pct_mcc":0.000484},{"rank_by_duration":99,"event_id":"1053_20220615T001500","start_time_utc":"2022-06-15T00:15:00","end_time_utc":"2022-06-15T10:15:00","year":2022,"duration_hours":10.0,"n_snapshots":40,"min_customers_out":4,"max_customers_out":1001,"mean_customers_out":195.425,"peak_out_pct_mcc":0.053837},{"rank_by_duration":100,"event_id":"1053_20220302T220000","start_time_utc":"2022-03-02T22:00:00","end_time_utc":"2022-03-03T08:00:00","year":2022,"duration_hours":10.0,"n_snapshots":40,"min_customers_out":4,"max_customers_out":627,"mean_customers_out":175.575,"peak_out_pct_mcc":0.033722},{"rank_by_duration":101,"event_id":"1053_20210830T114500","start_time_utc":"2021-08-30T11:45:00","end_time_utc":"2021-08-30T21:45:00","year":2021,"duration_hours":10.0,"n_snapshots":40,"min_customers_out":4,"max_customers_out":97,"mean_customers_out":36.25,"peak_out_pct_mcc":0.005217},{"rank_by_duration":102,"event_id":"1053_20221125T123000","start_time_utc":"2022-11-25T12:30:00","end_time_utc":"2022-11-25T22:30:00","year":2022,"duration_hours":10.0,"n_snapshots":38,"min_customers_out":4,"max_customers_out":88,"mean_customers_out":60.474,"peak_out_pct_mcc":0.004733},{"rank_by_duration":103,"event_id":"1053_20240726T061500","start_time_utc":"2024-07-26T06:15:00","end_time_utc":"2024-07-26T16:15:00","year":2024,"duration_hours":10.0,"n_snapshots":40,"min_customers_out":4,"max_customers_out":64,"mean_customers_out":42.05,"peak_out_pct_mcc":0.003442},{"rank_by_duration":104,"event_id":"1053_20180711T140000","start_time_utc":"2018-07-11T14:00:00","end_time_utc":"2018-07-12T00:00:00","year":2018,"duration_hours":10.0,"n_snapshots":37,"min_customers_out":4,"max_customers_out":33,"mean_customers_out":21.568,"peak_out_pct_mcc":0.001775},{"rank_by_duration":105,"event_id":"1053_20250814T040000","start_time_utc":"2025-08-14T04:00:00","end_time_utc":"2025-08-14T14:00:00","year":2025,"duration_hours":10.0,"n_snapshots":40,"min_customers_out":4,"max_customers_out":22,"mean_customers_out":12.675,"peak_out_pct_mcc":0.001183},{"rank_by_duration":106,"event_id":"1053_20240521T181500","start_time_utc":"2024-05-21T18:15:00","end_time_utc":"2024-05-22T04:15:00","year":2024,"duration_hours":10.0,"n_snapshots":40,"min_customers_out":4,"max_customers_out":4,"mean_customers_out":4.0,"peak_out_pct_mcc":0.000215},{"rank_by_duration":107,"event_id":"1053_20251203T143000","start_time_utc":"2025-12-03T14:30:00","end_time_utc":"2025-12-04T00:15:00","year":2025,"duration_hours":9.75,"n_snapshots":37,"min_customers_out":4,"max_customers_out":27,"mean_customers_out":6.595,"peak_out_pct_mcc":0.001452},{"rank_by_duration":108,"event_id":"1053_20171210T094500","start_time_utc":"2017-12-10T09:45:00","end_time_utc":"2017-12-10T19:30:00","year":2017,"duration_hours":9.75,"n_snapshots":38,"min_customers_out":1,"max_customers_out":24,"mean_customers_out":6.474,"peak_out_pct_mcc":0.001291},{"rank_by_duration":109,"event_id":"1053_20240826T124500","start_time_utc":"2024-08-26T12:45:00","end_time_utc":"2024-08-26T22:30:00","year":2024,"duration_hours":9.75,"n_snapshots":39,"min_customers_out":1,"max_customers_out":10,"mean_customers_out":5.154,"peak_out_pct_mcc":0.000538},{"rank_by_duration":110,"event_id":"1053_20230501T070000","start_time_utc":"2023-05-01T07:00:00","end_time_utc":"2023-05-01T16:45:00","year":2023,"duration_hours":9.75,"n_snapshots":39,"min_customers_out":4,"max_customers_out":4,"mean_customers_out":4.0,"peak_out_pct_mcc":0.000215},{"rank_by_duration":111,"event_id":"1053_20230430T141500","start_time_utc":"2023-04-30T14:15:00","end_time_utc":"2023-04-30T23:45:00","year":2023,"duration_hours":9.5,"n_snapshots":38,"min_customers_out":4,"max_customers_out":192,"mean_customers_out":50.158,"peak_out_pct_mcc":0.010326},{"rank_by_duration":112,"event_id":"1053_20210621T141500","start_time_utc":"2021-06-21T14:15:00","end_time_utc":"2021-06-21T23:45:00","year":2021,"duration_hours":9.5,"n_snapshots":38,"min_customers_out":4,"max_customers_out":120,"mean_customers_out":24.553,"peak_out_pct_mcc":0.006454},{"rank_by_duration":113,"event_id":"1053_20171011T021500","start_time_utc":"2017-10-11T02:15:00","end_time_utc":"2017-10-11T11:45:00","year":2017,"duration_hours":9.5,"n_snapshots":38,"min_customers_out":3,"max_customers_out":68,"mean_customers_out":32.658,"peak_out_pct_mcc":0.003657},{"rank_by_duration":114,"event_id":"1053_20240606T001500","start_time_utc":"2024-06-06T00:15:00","end_time_utc":"2024-06-06T09:45:00","year":2024,"duration_hours":9.5,"n_snapshots":38,"min_customers_out":4,"max_customers_out":17,"mean_customers_out":6.526,"peak_out_pct_mcc":0.000914},{"rank_by_duration":115,"event_id":"1053_20230818T074500","start_time_utc":"2023-08-18T07:45:00","end_time_utc":"2023-08-18T17:15:00","year":2023,"duration_hours":9.5,"n_snapshots":38,"min_customers_out":4,"max_customers_out":12,"mean_customers_out":4.526,"peak_out_pct_mcc":0.000645},{"rank_by_duration":116,"event_id":"1053_20250818T181500","start_time_utc":"2025-08-18T18:15:00","end_time_utc":"2025-08-19T03:45:00","year":2025,"duration_hours":9.5,"n_snapshots":35,"min_customers_out":4,"max_customers_out":6,"mean_customers_out":5.714,"peak_out_pct_mcc":0.000323},{"rank_by_duration":117,"event_id":"1053_20251029T124500","start_time_utc":"2025-10-29T12:45:00","end_time_utc":"2025-10-29T22:00:00","year":2025,"duration_hours":9.25,"n_snapshots":36,"min_customers_out":4,"max_customers_out":246,"mean_customers_out":73.639,"peak_out_pct_mcc":0.013231},{"rank_by_duration":118,"event_id":"1053_20190808T094500","start_time_utc":"2019-08-08T09:45:00","end_time_utc":"2019-08-08T19:00:00","year":2019,"duration_hours":9.25,"n_snapshots":37,"min_customers_out":4,"max_customers_out":175,"mean_customers_out":8.703,"peak_out_pct_mcc":0.009412},{"rank_by_duration":119,"event_id":"1053_20190821T090000","start_time_utc":"2019-08-21T09:00:00","end_time_utc":"2019-08-21T18:15:00","year":2019,"duration_hours":9.25,"n_snapshots":37,"min_customers_out":4,"max_customers_out":151,"mean_customers_out":19.784,"peak_out_pct_mcc":0.008121},{"rank_by_duration":120,"event_id":"1053_20230918T043000","start_time_utc":"2023-09-18T04:30:00","end_time_utc":"2023-09-18T13:45:00","year":2023,"duration_hours":9.25,"n_snapshots":37,"min_customers_out":4,"max_customers_out":87,"mean_customers_out":12.973,"peak_out_pct_mcc":0.004679},{"rank_by_duration":121,"event_id":"1053_20220222T150000","start_time_utc":"2022-02-22T15:00:00","end_time_utc":"2022-02-23T00:15:00","year":2022,"duration_hours":9.25,"n_snapshots":36,"min_customers_out":4,"max_customers_out":32,"mean_customers_out":6.75,"peak_out_pct_mcc":0.001721},{"rank_by_duration":122,"event_id":"1053_20250129T134500","start_time_utc":"2025-01-29T13:45:00","end_time_utc":"2025-01-29T23:00:00","year":2025,"duration_hours":9.25,"n_snapshots":37,"min_customers_out":4,"max_customers_out":8,"mean_customers_out":5.351,"peak_out_pct_mcc":0.00043},{"rank_by_duration":123,"event_id":"1053_20230122T083000","start_time_utc":"2023-01-22T08:30:00","end_time_utc":"2023-01-22T17:45:00","year":2023,"duration_hours":9.25,"n_snapshots":37,"min_customers_out":4,"max_customers_out":6,"mean_customers_out":4.27,"peak_out_pct_mcc":0.000323},{"rank_by_duration":124,"event_id":"1053_20251111T144500","start_time_utc":"2025-11-11T14:45:00","end_time_utc":"2025-11-12T00:00:00","year":2025,"duration_hours":9.25,"n_snapshots":37,"min_customers_out":4,"max_customers_out":4,"mean_customers_out":4.0,"peak_out_pct_mcc":0.000215},{"rank_by_duration":125,"event_id":"1053_20200114T064500","start_time_utc":"2020-01-14T06:45:00","end_time_utc":"2020-01-14T16:00:00","year":2020,"duration_hours":9.25,"n_snapshots":37,"min_customers_out":4,"max_customers_out":4,"mean_customers_out":4.0,"peak_out_pct_mcc":0.000215},{"rank_by_duration":126,"event_id":"1053_20190911T120000","start_time_utc":"2019-09-11T12:00:00","end_time_utc":"2019-09-11T21:00:00","year":2019,"duration_hours":9.0,"n_snapshots":36,"min_customers_out":4,"max_customers_out":954,"mean_customers_out":48.25,"peak_out_pct_mcc":0.05131},{"rank_by_duration":127,"event_id":"1053_20230815T214500","start_time_utc":"2023-08-15T21:45:00","end_time_utc":"2023-08-16T06:45:00","year":2023,"duration_hours":9.0,"n_snapshots":35,"min_customers_out":4,"max_customers_out":816,"mean_customers_out":106.143,"peak_out_pct_mcc":0.043887},{"rank_by_duration":128,"event_id":"1053_20200712T231500","start_time_utc":"2020-07-12T23:15:00","end_time_utc":"2020-07-13T08:15:00","year":2020,"duration_hours":9.0,"n_snapshots":36,"min_customers_out":4,"max_customers_out":381,"mean_customers_out":143.361,"peak_out_pct_mcc":0.020492},{"rank_by_duration":129,"event_id":"1053_20190819T191500","start_time_utc":"2019-08-19T19:15:00","end_time_utc":"2019-08-20T04:15:00","year":2019,"duration_hours":9.0,"n_snapshots":36,"min_customers_out":4,"max_customers_out":141,"mean_customers_out":59.861,"peak_out_pct_mcc":0.007583},{"rank_by_duration":130,"event_id":"1053_20220523T063000","start_time_utc":"2022-05-23T06:30:00","end_time_utc":"2022-05-23T15:30:00","year":2022,"duration_hours":9.0,"n_snapshots":36,"min_customers_out":4,"max_customers_out":44,"mean_customers_out":15.028,"peak_out_pct_mcc":0.002366},{"rank_by_duration":131,"event_id":"1053_20250205T141500","start_time_utc":"2025-02-05T14:15:00","end_time_utc":"2025-02-05T23:15:00","year":2025,"duration_hours":9.0,"n_snapshots":36,"min_customers_out":4,"max_customers_out":14,"mean_customers_out":10.167,"peak_out_pct_mcc":0.000753},{"rank_by_duration":132,"event_id":"1053_20250220T141500","start_time_utc":"2025-02-20T14:15:00","end_time_utc":"2025-02-20T23:15:00","year":2025,"duration_hours":9.0,"n_snapshots":36,"min_customers_out":4,"max_customers_out":11,"mean_customers_out":5.222,"peak_out_pct_mcc":0.000592},{"rank_by_duration":133,"event_id":"1053_20241212T130000","start_time_utc":"2024-12-12T13:00:00","end_time_utc":"2024-12-12T22:00:00","year":2024,"duration_hours":9.0,"n_snapshots":34,"min_customers_out":4,"max_customers_out":8,"mean_customers_out":5.118,"peak_out_pct_mcc":0.00043},{"rank_by_duration":134,"event_id":"1053_20250224T134500","start_time_utc":"2025-02-24T13:45:00","end_time_utc":"2025-02-24T22:45:00","year":2025,"duration_hours":9.0,"n_snapshots":36,"min_customers_out":4,"max_customers_out":6,"mean_customers_out":4.444,"peak_out_pct_mcc":0.000323},{"rank_by_duration":135,"event_id":"1053_20250130T151500","start_time_utc":"2025-01-30T15:15:00","end_time_utc":"2025-01-31T00:15:00","year":2025,"duration_hours":9.0,"n_snapshots":36,"min_customers_out":4,"max_customers_out":6,"mean_customers_out":4.444,"peak_out_pct_mcc":0.000323},{"rank_by_duration":136,"event_id":"1053_20220331T043000","start_time_utc":"2022-03-31T04:30:00","end_time_utc":"2022-03-31T13:15:00","year":2022,"duration_hours":8.75,"n_snapshots":35,"min_customers_out":22,"max_customers_out":479,"mean_customers_out":224.686,"peak_out_pct_mcc":0.025762},{"rank_by_duration":137,"event_id":"1053_20250603T140000","start_time_utc":"2025-06-03T14:00:00","end_time_utc":"2025-06-03T22:45:00","year":2025,"duration_hours":8.75,"n_snapshots":33,"min_customers_out":4,"max_customers_out":319,"mean_customers_out":68.97,"peak_out_pct_mcc":0.017157},{"rank_by_duration":138,"event_id":"1053_20180829T230000","start_time_utc":"2018-08-29T23:00:00","end_time_utc":"2018-08-30T07:45:00","year":2018,"duration_hours":8.75,"n_snapshots":34,"min_customers_out":4,"max_customers_out":130,"mean_customers_out":70.706,"peak_out_pct_mcc":0.006992},{"rank_by_duration":139,"event_id":"1053_20180605T130000","start_time_utc":"2018-06-05T13:00:00","end_time_utc":"2018-06-05T21:45:00","year":2018,"duration_hours":8.75,"n_snapshots":35,"min_customers_out":4,"max_customers_out":82,"mean_customers_out":25.429,"peak_out_pct_mcc":0.00441},{"rank_by_duration":140,"event_id":"1053_20200428T124500","start_time_utc":"2020-04-28T12:45:00","end_time_utc":"2020-04-28T21:30:00","year":2020,"duration_hours":8.75,"n_snapshots":35,"min_customers_out":4,"max_customers_out":75,"mean_customers_out":15.314,"peak_out_pct_mcc":0.004034},{"rank_by_duration":141,"event_id":"1053_20191028T131500","start_time_utc":"2019-10-28T13:15:00","end_time_utc":"2019-10-28T22:00:00","year":2019,"duration_hours":8.75,"n_snapshots":33,"min_customers_out":4,"max_customers_out":53,"mean_customers_out":22.273,"peak_out_pct_mcc":0.002851},{"rank_by_duration":142,"event_id":"1053_20230421T030000","start_time_utc":"2023-04-21T03:00:00","end_time_utc":"2023-04-21T11:45:00","year":2023,"duration_hours":8.75,"n_snapshots":35,"min_customers_out":22,"max_customers_out":52,"mean_customers_out":30.4,"peak_out_pct_mcc":0.002797},{"rank_by_duration":143,"event_id":"1053_20191004T213000","start_time_utc":"2019-10-04T21:30:00","end_time_utc":"2019-10-05T06:15:00","year":2019,"duration_hours":8.75,"n_snapshots":33,"min_customers_out":4,"max_customers_out":37,"mean_customers_out":11.97,"peak_out_pct_mcc":0.00199},{"rank_by_duration":144,"event_id":"1053_20240517T190000","start_time_utc":"2024-05-17T19:00:00","end_time_utc":"2024-05-18T03:45:00","year":2024,"duration_hours":8.75,"n_snapshots":34,"min_customers_out":4,"max_customers_out":36,"mean_customers_out":11.0,"peak_out_pct_mcc":0.001936},{"rank_by_duration":145,"event_id":"1053_20190320T134500","start_time_utc":"2019-03-20T13:45:00","end_time_utc":"2019-03-20T22:30:00","year":2019,"duration_hours":8.75,"n_snapshots":35,"min_customers_out":7,"max_customers_out":35,"mean_customers_out":8.657,"peak_out_pct_mcc":0.001882},{"rank_by_duration":146,"event_id":"1053_20220818T054500","start_time_utc":"2022-08-18T05:45:00","end_time_utc":"2022-08-18T14:30:00","year":2022,"duration_hours":8.75,"n_snapshots":35,"min_customers_out":4,"max_customers_out":26,"mean_customers_out":9.8,"peak_out_pct_mcc":0.001398},{"rank_by_duration":147,"event_id":"1053_20190619T104500","start_time_utc":"2019-06-19T10:45:00","end_time_utc":"2019-06-19T19:30:00","year":2019,"duration_hours":8.75,"n_snapshots":34,"min_customers_out":4,"max_customers_out":26,"mean_customers_out":10.324,"peak_out_pct_mcc":0.001398},{"rank_by_duration":148,"event_id":"1053_20250207T111500","start_time_utc":"2025-02-07T11:15:00","end_time_utc":"2025-02-07T20:00:00","year":2025,"duration_hours":8.75,"n_snapshots":35,"min_customers_out":4,"max_customers_out":23,"mean_customers_out":9.114,"peak_out_pct_mcc":0.001237},{"rank_by_duration":149,"event_id":"1053_20230526T031500","start_time_utc":"2023-05-26T03:15:00","end_time_utc":"2023-05-26T12:00:00","year":2023,"duration_hours":8.75,"n_snapshots":35,"min_customers_out":4,"max_customers_out":4,"mean_customers_out":4.0,"peak_out_pct_mcc":0.000215},{"rank_by_duration":150,"event_id":"1053_20190903T041500","start_time_utc":"2019-09-03T04:15:00","end_time_utc":"2019-09-03T13:00:00","year":2019,"duration_hours":8.75,"n_snapshots":35,"min_customers_out":4,"max_customers_out":4,"mean_customers_out":4.0,"peak_out_pct_mcc":0.000215},{"rank_by_duration":151,"event_id":"1053_20241115T024500","start_time_utc":"2024-11-15T02:45:00","end_time_utc":"2024-11-15T11:15:00","year":2024,"duration_hours":8.5,"n_snapshots":34,"min_customers_out":21,"max_customers_out":22,"mean_customers_out":21.059,"peak_out_pct_mcc":0.001183},{"rank_by_duration":152,"event_id":"1053_20250610T094500","start_time_utc":"2025-06-10T09:45:00","end_time_utc":"2025-06-10T18:15:00","year":2025,"duration_hours":8.5,"n_snapshots":32,"min_customers_out":4,"max_customers_out":6,"mean_customers_out":4.219,"peak_out_pct_mcc":0.000323},{"rank_by_duration":153,"event_id":"1053_20201102T161500","start_time_utc":"2020-11-02T16:15:00","end_time_utc":"2020-11-03T00:45:00","year":2020,"duration_hours":8.5,"n_snapshots":33,"min_customers_out":4,"max_customers_out":6,"mean_customers_out":4.333,"peak_out_pct_mcc":0.000323},{"rank_by_duration":154,"event_id":"1053_20230220T040000","start_time_utc":"2023-02-20T04:00:00","end_time_utc":"2023-02-20T12:30:00","year":2023,"duration_hours":8.5,"n_snapshots":34,"min_customers_out":4,"max_customers_out":4,"mean_customers_out":4.0,"peak_out_pct_mcc":0.000215},{"rank_by_duration":155,"event_id":"1053_20180715T030000","start_time_utc":"2018-07-15T03:00:00","end_time_utc":"2018-07-15T11:30:00","year":2018,"duration_hours":8.5,"n_snapshots":34,"min_customers_out":4,"max_customers_out":4,"mean_customers_out":4.0,"peak_out_pct_mcc":0.000215},{"rank_by_duration":156,"event_id":"1053_20190414T094500","start_time_utc":"2019-04-14T09:45:00","end_time_utc":"2019-04-14T18:00:00","year":2019,"duration_hours":8.25,"n_snapshots":33,"min_customers_out":4,"max_customers_out":493,"mean_customers_out":172.848,"peak_out_pct_mcc":0.026515},{"rank_by_duration":157,"event_id":"1053_20210607T014500","start_time_utc":"2021-06-07T01:45:00","end_time_utc":"2021-06-07T10:00:00","year":2021,"duration_hours":8.25,"n_snapshots":33,"min_customers_out":5,"max_customers_out":181,"mean_customers_out":114.939,"peak_out_pct_mcc":0.009735},{"rank_by_duration":158,"event_id":"1053_20200811T230000","start_time_utc":"2020-08-11T23:00:00","end_time_utc":"2020-08-12T07:15:00","year":2020,"duration_hours":8.25,"n_snapshots":31,"min_customers_out":4,"max_customers_out":164,"mean_customers_out":100.194,"peak_out_pct_mcc":0.008821},{"rank_by_duration":159,"event_id":"1053_20190713T101500","start_time_utc":"2019-07-13T10:15:00","end_time_utc":"2019-07-13T18:30:00","year":2019,"duration_hours":8.25,"n_snapshots":33,"min_customers_out":4,"max_customers_out":131,"mean_customers_out":38.758,"peak_out_pct_mcc":0.007046},{"rank_by_duration":160,"event_id":"1053_20240817T211500","start_time_utc":"2024-08-17T21:15:00","end_time_utc":"2024-08-18T05:30:00","year":2024,"duration_hours":8.25,"n_snapshots":31,"min_customers_out":4,"max_customers_out":64,"mean_customers_out":28.065,"peak_out_pct_mcc":0.003442},{"rank_by_duration":161,"event_id":"1053_20180328T131500","start_time_utc":"2018-03-28T13:15:00","end_time_utc":"2018-03-28T21:30:00","year":2018,"duration_hours":8.25,"n_snapshots":33,"min_customers_out":4,"max_customers_out":60,"mean_customers_out":21.667,"peak_out_pct_mcc":0.003227},{"rank_by_duration":162,"event_id":"1053_20180515T120000","start_time_utc":"2018-05-15T12:00:00","end_time_utc":"2018-05-15T20:15:00","year":2018,"duration_hours":8.25,"n_snapshots":32,"min_customers_out":4,"max_customers_out":59,"mean_customers_out":16.594,"peak_out_pct_mcc":0.003173},{"rank_by_duration":163,"event_id":"1053_20210306T190000","start_time_utc":"2021-03-06T19:00:00","end_time_utc":"2021-03-07T03:15:00","year":2021,"duration_hours":8.25,"n_snapshots":33,"min_customers_out":4,"max_customers_out":46,"mean_customers_out":5.273,"peak_out_pct_mcc":0.002474},{"rank_by_duration":164,"event_id":"1053_20180320T124500","start_time_utc":"2018-03-20T12:45:00","end_time_utc":"2018-03-20T21:00:00","year":2018,"duration_hours":8.25,"n_snapshots":30,"min_customers_out":4,"max_customers_out":40,"mean_customers_out":14.467,"peak_out_pct_mcc":0.002151},{"rank_by_duration":165,"event_id":"1053_20250630T173000","start_time_utc":"2025-06-30T17:30:00","end_time_utc":"2025-07-01T01:45:00","year":2025,"duration_hours":8.25,"n_snapshots":32,"min_customers_out":4,"max_customers_out":17,"mean_customers_out":6.562,"peak_out_pct_mcc":0.000914},{"rank_by_duration":166,"event_id":"1053_20251112T151500","start_time_utc":"2025-11-12T15:15:00","end_time_utc":"2025-11-12T23:30:00","year":2025,"duration_hours":8.25,"n_snapshots":33,"min_customers_out":4,"max_customers_out":11,"mean_customers_out":5.818,"peak_out_pct_mcc":0.000592},{"rank_by_duration":167,"event_id":"1053_20241217T143000","start_time_utc":"2024-12-17T14:30:00","end_time_utc":"2024-12-17T22:45:00","year":2024,"duration_hours":8.25,"n_snapshots":33,"min_customers_out":4,"max_customers_out":11,"mean_customers_out":6.121,"peak_out_pct_mcc":0.000592},{"rank_by_duration":168,"event_id":"1053_20250624T134500","start_time_utc":"2025-06-24T13:45:00","end_time_utc":"2025-06-24T22:00:00","year":2025,"duration_hours":8.25,"n_snapshots":31,"min_customers_out":4,"max_customers_out":8,"mean_customers_out":4.645,"peak_out_pct_mcc":0.00043},{"rank_by_duration":169,"event_id":"1053_20241230T134500","start_time_utc":"2024-12-30T13:45:00","end_time_utc":"2024-12-30T22:00:00","year":2024,"duration_hours":8.25,"n_snapshots":33,"min_customers_out":4,"max_customers_out":8,"mean_customers_out":6.061,"peak_out_pct_mcc":0.00043},{"rank_by_duration":170,"event_id":"1053_20250826T043000","start_time_utc":"2025-08-26T04:30:00","end_time_utc":"2025-08-26T12:45:00","year":2025,"duration_hours":8.25,"n_snapshots":33,"min_customers_out":4,"max_customers_out":4,"mean_customers_out":4.0,"peak_out_pct_mcc":0.000215},{"rank_by_duration":171,"event_id":"1053_20240827T140000","start_time_utc":"2024-08-27T14:00:00","end_time_utc":"2024-08-27T22:15:00","year":2024,"duration_hours":8.25,"n_snapshots":33,"min_customers_out":4,"max_customers_out":4,"mean_customers_out":4.0,"peak_out_pct_mcc":0.000215},{"rank_by_duration":172,"event_id":"1053_20190609T144500","start_time_utc":"2019-06-09T14:45:00","end_time_utc":"2019-06-09T23:00:00","year":2019,"duration_hours":8.25,"n_snapshots":33,"min_customers_out":4,"max_customers_out":4,"mean_customers_out":4.0,"peak_out_pct_mcc":0.000215},{"rank_by_duration":173,"event_id":"1053_20240617T191500","start_time_utc":"2024-06-17T19:15:00","end_time_utc":"2024-06-18T03:15:00","year":2024,"duration_hours":8.0,"n_snapshots":32,"min_customers_out":14,"max_customers_out":899,"mean_customers_out":397.375,"peak_out_pct_mcc":0.048352},{"rank_by_duration":174,"event_id":"1053_20250626T010000","start_time_utc":"2025-06-26T01:00:00","end_time_utc":"2025-06-26T09:00:00","year":2025,"duration_hours":8.0,"n_snapshots":32,"min_customers_out":4,"max_customers_out":701,"mean_customers_out":265.469,"peak_out_pct_mcc":0.037702},{"rank_by_duration":175,"event_id":"1053_20230626T081500","start_time_utc":"2023-06-26T08:15:00","end_time_utc":"2023-06-26T16:15:00","year":2023,"duration_hours":8.0,"n_snapshots":32,"min_customers_out":4,"max_customers_out":352,"mean_customers_out":133.25,"peak_out_pct_mcc":0.018932},{"rank_by_duration":176,"event_id":"1053_20250503T093000","start_time_utc":"2025-05-03T09:30:00","end_time_utc":"2025-05-03T17:30:00","year":2025,"duration_hours":8.0,"n_snapshots":32,"min_customers_out":5,"max_customers_out":276,"mean_customers_out":109.594,"peak_out_pct_mcc":0.014844},{"rank_by_duration":177,"event_id":"1053_20190308T171500","start_time_utc":"2019-03-08T17:15:00","end_time_utc":"2019-03-09T01:15:00","year":2019,"duration_hours":8.0,"n_snapshots":32,"min_customers_out":4,"max_customers_out":177,"mean_customers_out":47.031,"peak_out_pct_mcc":0.00952},{"rank_by_duration":178,"event_id":"1053_20200719T101500","start_time_utc":"2020-07-19T10:15:00","end_time_utc":"2020-07-19T18:15:00","year":2020,"duration_hours":8.0,"n_snapshots":32,"min_customers_out":4,"max_customers_out":172,"mean_customers_out":25.0,"peak_out_pct_mcc":0.009251},{"rank_by_duration":179,"event_id":"1053_20240518T061500","start_time_utc":"2024-05-18T06:15:00","end_time_utc":"2024-05-18T14:15:00","year":2024,"duration_hours":8.0,"n_snapshots":32,"min_customers_out":27,"max_customers_out":121,"mean_customers_out":43.812,"peak_out_pct_mcc":0.006508},{"rank_by_duration":180,"event_id":"1053_20220103T014500","start_time_utc":"2022-01-03T01:45:00","end_time_utc":"2022-01-03T09:45:00","year":2022,"duration_hours":8.0,"n_snapshots":30,"min_customers_out":4,"max_customers_out":105,"mean_customers_out":18.7,"peak_out_pct_mcc":0.005647},{"rank_by_duration":181,"event_id":"1053_20220312T063000","start_time_utc":"2022-03-12T06:30:00","end_time_utc":"2022-03-12T14:30:00","year":2022,"duration_hours":8.0,"n_snapshots":31,"min_customers_out":4,"max_customers_out":41,"mean_customers_out":8.226,"peak_out_pct_mcc":0.002205},{"rank_by_duration":182,"event_id":"1053_20230719T161500","start_time_utc":"2023-07-19T16:15:00","end_time_utc":"2023-07-20T00:15:00","year":2023,"duration_hours":8.0,"n_snapshots":29,"min_customers_out":4,"max_customers_out":18,"mean_customers_out":4.966,"peak_out_pct_mcc":0.000968},{"rank_by_duration":183,"event_id":"1053_20230827T204500","start_time_utc":"2023-08-27T20:45:00","end_time_utc":"2023-08-28T04:45:00","year":2023,"duration_hours":8.0,"n_snapshots":30,"min_customers_out":4,"max_customers_out":16,"mean_customers_out":5.667,"peak_out_pct_mcc":0.000861},{"rank_by_duration":184,"event_id":"1053_20250730T141500","start_time_utc":"2025-07-30T14:15:00","end_time_utc":"2025-07-30T22:15:00","year":2025,"duration_hours":8.0,"n_snapshots":30,"min_customers_out":4,"max_customers_out":12,"mean_customers_out":4.933,"peak_out_pct_mcc":0.000645},{"rank_by_duration":185,"event_id":"1053_20240904T131500","start_time_utc":"2024-09-04T13:15:00","end_time_utc":"2024-09-04T21:15:00","year":2024,"duration_hours":8.0,"n_snapshots":32,"min_customers_out":4,"max_customers_out":12,"mean_customers_out":5.469,"peak_out_pct_mcc":0.000645},{"rank_by_duration":186,"event_id":"1053_20250113T141500","start_time_utc":"2025-01-13T14:15:00","end_time_utc":"2025-01-13T22:15:00","year":2025,"duration_hours":8.0,"n_snapshots":32,"min_customers_out":4,"max_customers_out":10,"mean_customers_out":5.438,"peak_out_pct_mcc":0.000538},{"rank_by_duration":187,"event_id":"1053_20230703T123000","start_time_utc":"2023-07-03T12:30:00","end_time_utc":"2023-07-03T20:30:00","year":2023,"duration_hours":8.0,"n_snapshots":32,"min_customers_out":4,"max_customers_out":7,"mean_customers_out":4.281,"peak_out_pct_mcc":0.000376},{"rank_by_duration":188,"event_id":"1053_20251011T060000","start_time_utc":"2025-10-11T06:00:00","end_time_utc":"2025-10-11T14:00:00","year":2025,"duration_hours":8.0,"n_snapshots":32,"min_customers_out":4,"max_customers_out":4,"mean_customers_out":4.0,"peak_out_pct_mcc":0.000215},{"rank_by_duration":189,"event_id":"1053_20241121T134500","start_time_utc":"2024-11-21T13:45:00","end_time_utc":"2024-11-21T21:45:00","year":2024,"duration_hours":8.0,"n_snapshots":30,"min_customers_out":4,"max_customers_out":4,"mean_customers_out":4.0,"peak_out_pct_mcc":0.000215},{"rank_by_duration":190,"event_id":"1053_20230416T114500","start_time_utc":"2023-04-16T11:45:00","end_time_utc":"2023-04-16T19:45:00","year":2023,"duration_hours":8.0,"n_snapshots":32,"min_customers_out":4,"max_customers_out":4,"mean_customers_out":4.0,"peak_out_pct_mcc":0.000215},{"rank_by_duration":191,"event_id":"1053_20210829T061500","start_time_utc":"2021-08-29T06:15:00","end_time_utc":"2021-08-29T14:15:00","year":2021,"duration_hours":8.0,"n_snapshots":32,"min_customers_out":4,"max_customers_out":4,"mean_customers_out":4.0,"peak_out_pct_mcc":0.000215},{"rank_by_duration":192,"event_id":"1053_20191030T090000","start_time_utc":"2019-10-30T09:00:00","end_time_utc":"2019-10-30T17:00:00","year":2019,"duration_hours":8.0,"n_snapshots":31,"min_customers_out":4,"max_customers_out":4,"mean_customers_out":4.0,"peak_out_pct_mcc":0.000215},{"rank_by_duration":193,"event_id":"1053_20191029T130000","start_time_utc":"2019-10-29T13:00:00","end_time_utc":"2019-10-29T21:00:00","year":2019,"duration_hours":8.0,"n_snapshots":32,"min_customers_out":4,"max_customers_out":4,"mean_customers_out":4.0,"peak_out_pct_mcc":0.000215},{"rank_by_duration":194,"event_id":"1053_20180614T044500","start_time_utc":"2018-06-14T04:45:00","end_time_utc":"2018-06-14T12:45:00","year":2018,"duration_hours":8.0,"n_snapshots":32,"min_customers_out":4,"max_customers_out":4,"mean_customers_out":4.0,"peak_out_pct_mcc":0.000215},{"rank_by_duration":195,"event_id":"1053_20191022T133000","start_time_utc":"2019-10-22T13:30:00","end_time_utc":"2019-10-22T21:15:00","year":2019,"duration_hours":7.75,"n_snapshots":30,"min_customers_out":4,"max_customers_out":1391,"mean_customers_out":60.167,"peak_out_pct_mcc":0.074813},{"rank_by_duration":196,"event_id":"1053_20190512T130000","start_time_utc":"2019-05-12T13:00:00","end_time_utc":"2019-05-12T20:45:00","year":2019,"duration_hours":7.75,"n_snapshots":31,"min_customers_out":4,"max_customers_out":1034,"mean_customers_out":337.452,"peak_out_pct_mcc":0.055612},{"rank_by_duration":197,"event_id":"1053_20250623T233000","start_time_utc":"2025-06-23T23:30:00","end_time_utc":"2025-06-24T07:15:00","year":2025,"duration_hours":7.75,"n_snapshots":31,"min_customers_out":4,"max_customers_out":428,"mean_customers_out":96.032,"peak_out_pct_mcc":0.023019},{"rank_by_duration":198,"event_id":"1053_20250315T190000","start_time_utc":"2025-03-15T19:00:00","end_time_utc":"2025-03-16T02:45:00","year":2025,"duration_hours":7.75,"n_snapshots":30,"min_customers_out":4,"max_customers_out":353,"mean_customers_out":53.633,"peak_out_pct_mcc":0.018986},{"rank_by_duration":199,"event_id":"1053_20231016T081500","start_time_utc":"2023-10-16T08:15:00","end_time_utc":"2023-10-16T16:00:00","year":2023,"duration_hours":7.75,"n_snapshots":31,"min_customers_out":209,"max_customers_out":221,"mean_customers_out":212.258,"peak_out_pct_mcc":0.011886},{"rank_by_duration":200,"event_id":"1053_20230725T124500","start_time_utc":"2023-07-25T12:45:00","end_time_utc":"2023-07-25T20:30:00","year":2023,"duration_hours":7.75,"n_snapshots":30,"min_customers_out":209,"max_customers_out":213,"mean_customers_out":209.267,"peak_out_pct_mcc":0.011456}]}