{"fips":"51630","state":"VA","county":"Fredericksburg","tier":"green","quotable":true,"n_events_total":2577,"observation_years":11.16723705,"mcc":14939.0,"rows_policy":"top_200_longest_events","rows_returned":200,"threshold_summary":{"2":{"qualifying_events":1129,"S_T":0.43810633,"lambda_T":101.09931353},"4":{"qualifying_events":539,"S_T":0.20915794,"lambda_T":48.26619131},"8":{"qualifying_events":144,"S_T":0.05587893,"lambda_T":12.89486373},"12":{"qualifying_events":51,"S_T":0.01979045,"lambda_T":4.5669309},"24":{"qualifying_events":12,"S_T":0.00465658,"lambda_T":1.07457198}},"events":[{"rank_by_duration":1,"event_id":"51630_20220103T141500","start_time_utc":"2022-01-03T14:15:00","end_time_utc":"2022-01-09T02:45:00","year":2022,"duration_hours":132.5,"n_snapshots":530,"min_customers_out":1,"max_customers_out":4952,"mean_customers_out":1295.362,"peak_out_pct_mcc":0.331481},{"rank_by_duration":2,"event_id":"51630_20180302T094500","start_time_utc":"2018-03-02T09:45:00","end_time_utc":"2018-03-06T01:00:00","year":2018,"duration_hours":87.25,"n_snapshots":349,"min_customers_out":51,"max_customers_out":3529,"mean_customers_out":1105.046,"peak_out_pct_mcc":0.236227},{"rank_by_duration":3,"event_id":"51630_20220622T134500","start_time_utc":"2022-06-22T13:45:00","end_time_utc":"2022-06-25T00:30:00","year":2022,"duration_hours":58.75,"n_snapshots":235,"min_customers_out":1,"max_customers_out":6612,"mean_customers_out":1714.298,"peak_out_pct_mcc":0.4426},{"rank_by_duration":4,"event_id":"51630_20180106T100000","start_time_utc":"2018-01-06T10:00:00","end_time_utc":"2018-01-08T19:45:00","year":2018,"duration_hours":57.75,"n_snapshots":227,"min_customers_out":1,"max_customers_out":29,"mean_customers_out":3.74,"peak_out_pct_mcc":0.001941},{"rank_by_duration":5,"event_id":"51630_20180703T001500","start_time_utc":"2018-07-03T00:15:00","end_time_utc":"2018-07-04T14:30:00","year":2018,"duration_hours":38.25,"n_snapshots":150,"min_customers_out":2,"max_customers_out":48,"mean_customers_out":22.38,"peak_out_pct_mcc":0.003213},{"rank_by_duration":6,"event_id":"51630_20190629T191500","start_time_utc":"2019-06-29T19:15:00","end_time_utc":"2019-07-01T04:45:00","year":2019,"duration_hours":33.5,"n_snapshots":134,"min_customers_out":1,"max_customers_out":680,"mean_customers_out":135.545,"peak_out_pct_mcc":0.045518},{"rank_by_duration":7,"event_id":"51630_20170301T190000","start_time_utc":"2017-03-01T19:00:00","end_time_utc":"2017-03-02T22:45:00","year":2017,"duration_hours":27.75,"n_snapshots":111,"min_customers_out":1,"max_customers_out":55,"mean_customers_out":34.099,"peak_out_pct_mcc":0.003682},{"rank_by_duration":8,"event_id":"51630_20210714T213000","start_time_utc":"2021-07-14T21:30:00","end_time_utc":"2021-07-16T00:00:00","year":2021,"duration_hours":26.5,"n_snapshots":106,"min_customers_out":1,"max_customers_out":1712,"mean_customers_out":591.858,"peak_out_pct_mcc":0.114599},{"rank_by_duration":9,"event_id":"51630_20180812T201500","start_time_utc":"2018-08-12T20:15:00","end_time_utc":"2018-08-13T22:15:00","year":2018,"duration_hours":26.0,"n_snapshots":104,"min_customers_out":1,"max_customers_out":498,"mean_customers_out":188.923,"peak_out_pct_mcc":0.033336},{"rank_by_duration":10,"event_id":"51630_20200824T213000","start_time_utc":"2020-08-24T21:30:00","end_time_utc":"2020-08-25T23:30:00","year":2020,"duration_hours":26.0,"n_snapshots":104,"min_customers_out":125,"max_customers_out":378,"mean_customers_out":159.183,"peak_out_pct_mcc":0.025303},{"rank_by_duration":11,"event_id":"51630_20220523T000000","start_time_utc":"2022-05-23T00:00:00","end_time_utc":"2022-05-24T01:30:00","year":2022,"duration_hours":25.5,"n_snapshots":101,"min_customers_out":1,"max_customers_out":234,"mean_customers_out":54.97,"peak_out_pct_mcc":0.015664},{"rank_by_duration":12,"event_id":"51630_20190820T220000","start_time_utc":"2019-08-20T22:00:00","end_time_utc":"2019-08-21T22:00:00","year":2019,"duration_hours":24.0,"n_snapshots":96,"min_customers_out":2,"max_customers_out":236,"mean_customers_out":36.458,"peak_out_pct_mcc":0.015798},{"rank_by_duration":13,"event_id":"51630_20210729T220000","start_time_utc":"2021-07-29T22:00:00","end_time_utc":"2021-07-30T20:15:00","year":2021,"duration_hours":22.25,"n_snapshots":89,"min_customers_out":1,"max_customers_out":403,"mean_customers_out":128.157,"peak_out_pct_mcc":0.026976},{"rank_by_duration":14,"event_id":"51630_20240830T021500","start_time_utc":"2024-08-30T02:15:00","end_time_utc":"2024-08-30T23:00:00","year":2024,"duration_hours":20.75,"n_snapshots":83,"min_customers_out":1,"max_customers_out":732,"mean_customers_out":427.193,"peak_out_pct_mcc":0.048999},{"rank_by_duration":15,"event_id":"51630_20230515T164500","start_time_utc":"2023-05-15T16:45:00","end_time_utc":"2023-05-16T13:15:00","year":2023,"duration_hours":20.5,"n_snapshots":81,"min_customers_out":55,"max_customers_out":56,"mean_customers_out":55.012,"peak_out_pct_mcc":0.003749},{"rank_by_duration":16,"event_id":"51630_20160815T233000","start_time_utc":"2016-08-15T23:30:00","end_time_utc":"2016-08-16T19:00:00","year":2016,"duration_hours":19.5,"n_snapshots":78,"min_customers_out":2,"max_customers_out":3320,"mean_customers_out":617.5,"peak_out_pct_mcc":0.222237},{"rank_by_duration":17,"event_id":"51630_20250216T214500","start_time_utc":"2025-02-16T21:45:00","end_time_utc":"2025-02-17T17:00:00","year":2025,"duration_hours":19.25,"n_snapshots":77,"min_customers_out":12,"max_customers_out":104,"mean_customers_out":25.909,"peak_out_pct_mcc":0.006962},{"rank_by_duration":18,"event_id":"51630_20170714T214500","start_time_utc":"2017-07-14T21:45:00","end_time_utc":"2017-07-15T16:45:00","year":2017,"duration_hours":19.0,"n_snapshots":75,"min_customers_out":32,"max_customers_out":1218,"mean_customers_out":311.653,"peak_out_pct_mcc":0.081532},{"rank_by_duration":19,"event_id":"51630_20210814T013000","start_time_utc":"2021-08-14T01:30:00","end_time_utc":"2021-08-14T20:15:00","year":2021,"duration_hours":18.75,"n_snapshots":73,"min_customers_out":1,"max_customers_out":4,"mean_customers_out":1.781,"peak_out_pct_mcc":0.000268},{"rank_by_duration":20,"event_id":"51630_20200829T054500","start_time_utc":"2020-08-29T05:45:00","end_time_utc":"2020-08-29T23:45:00","year":2020,"duration_hours":18.0,"n_snapshots":72,"min_customers_out":11,"max_customers_out":71,"mean_customers_out":36.306,"peak_out_pct_mcc":0.004753},{"rank_by_duration":21,"event_id":"51630_20220713T003000","start_time_utc":"2022-07-13T00:30:00","end_time_utc":"2022-07-13T18:00:00","year":2022,"duration_hours":17.5,"n_snapshots":70,"min_customers_out":17,"max_customers_out":1033,"mean_customers_out":263.143,"peak_out_pct_mcc":0.069148},{"rank_by_duration":22,"event_id":"51630_20240410T173000","start_time_utc":"2024-04-10T17:30:00","end_time_utc":"2024-04-11T10:15:00","year":2024,"duration_hours":16.75,"n_snapshots":66,"min_customers_out":2,"max_customers_out":1809,"mean_customers_out":151.939,"peak_out_pct_mcc":0.121092},{"rank_by_duration":23,"event_id":"51630_20191101T021500","start_time_utc":"2019-11-01T02:15:00","end_time_utc":"2019-11-01T18:45:00","year":2019,"duration_hours":16.5,"n_snapshots":66,"min_customers_out":1,"max_customers_out":46,"mean_customers_out":31.136,"peak_out_pct_mcc":0.003079},{"rank_by_duration":24,"event_id":"51630_20160917T084500","start_time_utc":"2016-09-17T08:45:00","end_time_utc":"2016-09-18T00:30:00","year":2016,"duration_hours":15.75,"n_snapshots":63,"min_customers_out":7,"max_customers_out":139,"mean_customers_out":46.571,"peak_out_pct_mcc":0.009305},{"rank_by_duration":25,"event_id":"51630_20160528T000000","start_time_utc":"2016-05-28T00:00:00","end_time_utc":"2016-05-28T15:15:00","year":2016,"duration_hours":15.25,"n_snapshots":60,"min_customers_out":1,"max_customers_out":86,"mean_customers_out":20.5,"peak_out_pct_mcc":0.005757},{"rank_by_duration":26,"event_id":"51630_20170530T213000","start_time_utc":"2017-05-30T21:30:00","end_time_utc":"2017-05-31T12:30:00","year":2017,"duration_hours":15.0,"n_snapshots":58,"min_customers_out":1,"max_customers_out":460,"mean_customers_out":57.569,"peak_out_pct_mcc":0.030792},{"rank_by_duration":27,"event_id":"51630_20170528T030000","start_time_utc":"2017-05-28T03:00:00","end_time_utc":"2017-05-28T18:00:00","year":2017,"duration_hours":15.0,"n_snapshots":60,"min_customers_out":2,"max_customers_out":3,"mean_customers_out":2.117,"peak_out_pct_mcc":0.000201},{"rank_by_duration":28,"event_id":"51630_20180425T010000","start_time_utc":"2018-04-25T01:00:00","end_time_utc":"2018-04-25T15:45:00","year":2018,"duration_hours":14.75,"n_snapshots":59,"min_customers_out":1,"max_customers_out":82,"mean_customers_out":39.864,"peak_out_pct_mcc":0.005489},{"rank_by_duration":29,"event_id":"51630_20190903T024500","start_time_utc":"2019-09-03T02:45:00","end_time_utc":"2019-09-03T17:00:00","year":2019,"duration_hours":14.25,"n_snapshots":57,"min_customers_out":1,"max_customers_out":1059,"mean_customers_out":403.263,"peak_out_pct_mcc":0.070888},{"rank_by_duration":30,"event_id":"51630_20180624T193000","start_time_utc":"2018-06-24T19:30:00","end_time_utc":"2018-06-25T09:45:00","year":2018,"duration_hours":14.25,"n_snapshots":57,"min_customers_out":2,"max_customers_out":146,"mean_customers_out":36.088,"peak_out_pct_mcc":0.009773},{"rank_by_duration":31,"event_id":"51630_20250517T180000","start_time_utc":"2025-05-17T18:00:00","end_time_utc":"2025-05-18T08:15:00","year":2025,"duration_hours":14.25,"n_snapshots":57,"min_customers_out":1,"max_customers_out":2,"mean_customers_out":1.07,"peak_out_pct_mcc":0.000134},{"rank_by_duration":32,"event_id":"51630_20180416T024500","start_time_utc":"2018-04-16T02:45:00","end_time_utc":"2018-04-16T16:45:00","year":2018,"duration_hours":14.0,"n_snapshots":54,"min_customers_out":1,"max_customers_out":27,"mean_customers_out":4.796,"peak_out_pct_mcc":0.001807},{"rank_by_duration":33,"event_id":"51630_20191226T213000","start_time_utc":"2019-12-26T21:30:00","end_time_utc":"2019-12-27T11:30:00","year":2019,"duration_hours":14.0,"n_snapshots":56,"min_customers_out":5,"max_customers_out":5,"mean_customers_out":5.0,"peak_out_pct_mcc":0.000335},{"rank_by_duration":34,"event_id":"51630_20200808T104500","start_time_utc":"2020-08-08T10:45:00","end_time_utc":"2020-08-09T00:30:00","year":2020,"duration_hours":13.75,"n_snapshots":55,"min_customers_out":1,"max_customers_out":1,"mean_customers_out":1.0,"peak_out_pct_mcc":6.7e-05},{"rank_by_duration":35,"event_id":"51630_20180909T203000","start_time_utc":"2018-09-09T20:30:00","end_time_utc":"2018-09-10T10:00:00","year":2018,"duration_hours":13.5,"n_snapshots":54,"min_customers_out":1,"max_customers_out":158,"mean_customers_out":92.296,"peak_out_pct_mcc":0.010576},{"rank_by_duration":36,"event_id":"51630_20181024T230000","start_time_utc":"2018-10-24T23:00:00","end_time_utc":"2018-10-25T12:30:00","year":2018,"duration_hours":13.5,"n_snapshots":54,"min_customers_out":1,"max_customers_out":1,"mean_customers_out":1.0,"peak_out_pct_mcc":6.7e-05},{"rank_by_duration":37,"event_id":"51630_20250316T193000","start_time_utc":"2025-03-16T19:30:00","end_time_utc":"2025-03-17T08:45:00","year":2025,"duration_hours":13.25,"n_snapshots":53,"min_customers_out":61,"max_customers_out":61,"mean_customers_out":61.0,"peak_out_pct_mcc":0.004083},{"rank_by_duration":38,"event_id":"51630_20250401T033000","start_time_utc":"2025-04-01T03:30:00","end_time_utc":"2025-04-01T16:30:00","year":2025,"duration_hours":13.0,"n_snapshots":52,"min_customers_out":1,"max_customers_out":1818,"mean_customers_out":400.212,"peak_out_pct_mcc":0.121695},{"rank_by_duration":39,"event_id":"51630_20241121T024500","start_time_utc":"2024-11-21T02:45:00","end_time_utc":"2024-11-21T15:45:00","year":2024,"duration_hours":13.0,"n_snapshots":52,"min_customers_out":6,"max_customers_out":1034,"mean_customers_out":232.712,"peak_out_pct_mcc":0.069215},{"rank_by_duration":40,"event_id":"51630_20220117T131500","start_time_utc":"2022-01-17T13:15:00","end_time_utc":"2022-01-18T02:15:00","year":2022,"duration_hours":13.0,"n_snapshots":50,"min_customers_out":1,"max_customers_out":124,"mean_customers_out":15.2,"peak_out_pct_mcc":0.0083},{"rank_by_duration":41,"event_id":"51630_20180306T031500","start_time_utc":"2018-03-06T03:15:00","end_time_utc":"2018-03-06T16:15:00","year":2018,"duration_hours":13.0,"n_snapshots":52,"min_customers_out":75,"max_customers_out":95,"mean_customers_out":76.019,"peak_out_pct_mcc":0.006359},{"rank_by_duration":42,"event_id":"51630_20220705T013000","start_time_utc":"2022-07-05T01:30:00","end_time_utc":"2022-07-05T14:30:00","year":2022,"duration_hours":13.0,"n_snapshots":51,"min_customers_out":12,"max_customers_out":76,"mean_customers_out":74.745,"peak_out_pct_mcc":0.005087},{"rank_by_duration":43,"event_id":"51630_20200722T000000","start_time_utc":"2020-07-22T00:00:00","end_time_utc":"2020-07-22T13:00:00","year":2020,"duration_hours":13.0,"n_snapshots":52,"min_customers_out":1,"max_customers_out":61,"mean_customers_out":33.0,"peak_out_pct_mcc":0.004083},{"rank_by_duration":44,"event_id":"51630_20170408T083000","start_time_utc":"2017-04-08T08:30:00","end_time_utc":"2017-04-08T21:30:00","year":2017,"duration_hours":13.0,"n_snapshots":52,"min_customers_out":3,"max_customers_out":18,"mean_customers_out":4.731,"peak_out_pct_mcc":0.001205},{"rank_by_duration":45,"event_id":"51630_20221001T020000","start_time_utc":"2022-10-01T02:00:00","end_time_utc":"2022-10-01T14:45:00","year":2022,"duration_hours":12.75,"n_snapshots":51,"min_customers_out":1,"max_customers_out":30,"mean_customers_out":11.196,"peak_out_pct_mcc":0.002008},{"rank_by_duration":46,"event_id":"51630_20250705T114500","start_time_utc":"2025-07-05T11:45:00","end_time_utc":"2025-07-06T00:30:00","year":2025,"duration_hours":12.75,"n_snapshots":51,"min_customers_out":1,"max_customers_out":3,"mean_customers_out":1.216,"peak_out_pct_mcc":0.000201},{"rank_by_duration":47,"event_id":"51630_20251126T003000","start_time_utc":"2025-11-26T00:30:00","end_time_utc":"2025-11-26T13:00:00","year":2025,"duration_hours":12.5,"n_snapshots":50,"min_customers_out":10,"max_customers_out":799,"mean_customers_out":63.18,"peak_out_pct_mcc":0.053484},{"rank_by_duration":48,"event_id":"51630_20190624T221500","start_time_utc":"2019-06-24T22:15:00","end_time_utc":"2019-06-25T10:30:00","year":2019,"duration_hours":12.25,"n_snapshots":49,"min_customers_out":22,"max_customers_out":50,"mean_customers_out":24.429,"peak_out_pct_mcc":0.003347},{"rank_by_duration":49,"event_id":"51630_20220716T221500","start_time_utc":"2022-07-16T22:15:00","end_time_utc":"2022-07-17T10:30:00","year":2022,"duration_hours":12.25,"n_snapshots":49,"min_customers_out":1,"max_customers_out":4,"mean_customers_out":3.082,"peak_out_pct_mcc":0.000268},{"rank_by_duration":50,"event_id":"51630_20230820T234500","start_time_utc":"2023-08-20T23:45:00","end_time_utc":"2023-08-21T11:45:00","year":2023,"duration_hours":12.0,"n_snapshots":48,"min_customers_out":13,"max_customers_out":48,"mean_customers_out":28.75,"peak_out_pct_mcc":0.003213},{"rank_by_duration":51,"event_id":"51630_20251226T121500","start_time_utc":"2025-12-26T12:15:00","end_time_utc":"2025-12-27T00:15:00","year":2025,"duration_hours":12.0,"n_snapshots":48,"min_customers_out":6,"max_customers_out":21,"mean_customers_out":18.562,"peak_out_pct_mcc":0.001406},{"rank_by_duration":52,"event_id":"51630_20201205T214500","start_time_utc":"2020-12-05T21:45:00","end_time_utc":"2020-12-06T09:30:00","year":2020,"duration_hours":11.75,"n_snapshots":47,"min_customers_out":2,"max_customers_out":7,"mean_customers_out":2.319,"peak_out_pct_mcc":0.000469},{"rank_by_duration":53,"event_id":"51630_20250513T043000","start_time_utc":"2025-05-13T04:30:00","end_time_utc":"2025-05-13T16:15:00","year":2025,"duration_hours":11.75,"n_snapshots":47,"min_customers_out":1,"max_customers_out":6,"mean_customers_out":4.809,"peak_out_pct_mcc":0.000402},{"rank_by_duration":54,"event_id":"51630_20250606T131500","start_time_utc":"2025-06-06T13:15:00","end_time_utc":"2025-06-07T00:45:00","year":2025,"duration_hours":11.5,"n_snapshots":44,"min_customers_out":1,"max_customers_out":108,"mean_customers_out":15.182,"peak_out_pct_mcc":0.007229},{"rank_by_duration":55,"event_id":"51630_20181012T073000","start_time_utc":"2018-10-12T07:30:00","end_time_utc":"2018-10-12T19:00:00","year":2018,"duration_hours":11.5,"n_snapshots":46,"min_customers_out":1,"max_customers_out":5,"mean_customers_out":3.522,"peak_out_pct_mcc":0.000335},{"rank_by_duration":56,"event_id":"51630_20241015T211500","start_time_utc":"2024-10-15T21:15:00","end_time_utc":"2024-10-16T08:30:00","year":2024,"duration_hours":11.25,"n_snapshots":45,"min_customers_out":2,"max_customers_out":5371,"mean_customers_out":665.489,"peak_out_pct_mcc":0.359529},{"rank_by_duration":57,"event_id":"51630_20220510T040000","start_time_utc":"2022-05-10T04:00:00","end_time_utc":"2022-05-10T15:15:00","year":2022,"duration_hours":11.25,"n_snapshots":44,"min_customers_out":1,"max_customers_out":326,"mean_customers_out":302.0,"peak_out_pct_mcc":0.021822},{"rank_by_duration":58,"event_id":"51630_20201012T013000","start_time_utc":"2020-10-12T01:30:00","end_time_utc":"2020-10-12T12:45:00","year":2020,"duration_hours":11.25,"n_snapshots":45,"min_customers_out":3,"max_customers_out":227,"mean_customers_out":47.8,"peak_out_pct_mcc":0.015195},{"rank_by_duration":59,"event_id":"51630_20180501T201500","start_time_utc":"2018-05-01T20:15:00","end_time_utc":"2018-05-02T07:30:00","year":2018,"duration_hours":11.25,"n_snapshots":45,"min_customers_out":1,"max_customers_out":17,"mean_customers_out":4.911,"peak_out_pct_mcc":0.001138},{"rank_by_duration":60,"event_id":"51630_20200622T133000","start_time_utc":"2020-06-22T13:30:00","end_time_utc":"2020-06-23T00:45:00","year":2020,"duration_hours":11.25,"n_snapshots":45,"min_customers_out":1,"max_customers_out":11,"mean_customers_out":5.289,"peak_out_pct_mcc":0.000736},{"rank_by_duration":61,"event_id":"51630_20191212T113000","start_time_utc":"2019-12-12T11:30:00","end_time_utc":"2019-12-12T22:45:00","year":2019,"duration_hours":11.25,"n_snapshots":45,"min_customers_out":1,"max_customers_out":7,"mean_customers_out":3.244,"peak_out_pct_mcc":0.000469},{"rank_by_duration":62,"event_id":"51630_20180426T213000","start_time_utc":"2018-04-26T21:30:00","end_time_utc":"2018-04-27T08:45:00","year":2018,"duration_hours":11.25,"n_snapshots":45,"min_customers_out":1,"max_customers_out":2,"mean_customers_out":1.422,"peak_out_pct_mcc":0.000134},{"rank_by_duration":63,"event_id":"51630_20180814T230000","start_time_utc":"2018-08-14T23:00:00","end_time_utc":"2018-08-15T10:15:00","year":2018,"duration_hours":11.25,"n_snapshots":45,"min_customers_out":1,"max_customers_out":1,"mean_customers_out":1.0,"peak_out_pct_mcc":6.7e-05},{"rank_by_duration":64,"event_id":"51630_20220419T060000","start_time_utc":"2022-04-19T06:00:00","end_time_utc":"2022-04-19T17:00:00","year":2022,"duration_hours":11.0,"n_snapshots":44,"min_customers_out":7,"max_customers_out":1814,"mean_customers_out":669.614,"peak_out_pct_mcc":0.121427},{"rank_by_duration":65,"event_id":"51630_20201004T041500","start_time_utc":"2020-10-04T04:15:00","end_time_utc":"2020-10-04T15:15:00","year":2020,"duration_hours":11.0,"n_snapshots":44,"min_customers_out":1,"max_customers_out":40,"mean_customers_out":4.545,"peak_out_pct_mcc":0.002678},{"rank_by_duration":66,"event_id":"51630_20180902T210000","start_time_utc":"2018-09-02T21:00:00","end_time_utc":"2018-09-03T08:00:00","year":2018,"duration_hours":11.0,"n_snapshots":44,"min_customers_out":2,"max_customers_out":39,"mean_customers_out":5.114,"peak_out_pct_mcc":0.002611},{"rank_by_duration":67,"event_id":"51630_20250727T214500","start_time_utc":"2025-07-27T21:45:00","end_time_utc":"2025-07-28T08:45:00","year":2025,"duration_hours":11.0,"n_snapshots":43,"min_customers_out":1,"max_customers_out":11,"mean_customers_out":3.163,"peak_out_pct_mcc":0.000736},{"rank_by_duration":68,"event_id":"51630_20190924T193000","start_time_utc":"2019-09-24T19:30:00","end_time_utc":"2019-09-25T06:30:00","year":2019,"duration_hours":11.0,"n_snapshots":44,"min_customers_out":2,"max_customers_out":4,"mean_customers_out":3.091,"peak_out_pct_mcc":0.000268},{"rank_by_duration":69,"event_id":"51630_20250511T144500","start_time_utc":"2025-05-11T14:45:00","end_time_utc":"2025-05-12T01:45:00","year":2025,"duration_hours":11.0,"n_snapshots":44,"min_customers_out":1,"max_customers_out":1,"mean_customers_out":1.0,"peak_out_pct_mcc":6.7e-05},{"rank_by_duration":70,"event_id":"51630_20150529T053000","start_time_utc":"2015-05-29T05:30:00","end_time_utc":"2015-05-29T16:15:00","year":2015,"duration_hours":10.75,"n_snapshots":42,"min_customers_out":22,"max_customers_out":242,"mean_customers_out":131.905,"peak_out_pct_mcc":0.016199},{"rank_by_duration":71,"event_id":"51630_20230330T011500","start_time_utc":"2023-03-30T01:15:00","end_time_utc":"2023-03-30T12:00:00","year":2023,"duration_hours":10.75,"n_snapshots":43,"min_customers_out":6,"max_customers_out":39,"mean_customers_out":26.209,"peak_out_pct_mcc":0.002611},{"rank_by_duration":72,"event_id":"51630_20190319T150000","start_time_utc":"2019-03-19T15:00:00","end_time_utc":"2019-03-20T01:45:00","year":2019,"duration_hours":10.75,"n_snapshots":43,"min_customers_out":1,"max_customers_out":1,"mean_customers_out":1.0,"peak_out_pct_mcc":6.7e-05},{"rank_by_duration":73,"event_id":"51630_20170426T013000","start_time_utc":"2017-04-26T01:30:00","end_time_utc":"2017-04-26T12:00:00","year":2017,"duration_hours":10.5,"n_snapshots":39,"min_customers_out":1,"max_customers_out":167,"mean_customers_out":96.205,"peak_out_pct_mcc":0.011179},{"rank_by_duration":74,"event_id":"51630_20190323T024500","start_time_utc":"2019-03-23T02:45:00","end_time_utc":"2019-03-23T13:15:00","year":2019,"duration_hours":10.5,"n_snapshots":42,"min_customers_out":1,"max_customers_out":7,"mean_customers_out":3.571,"peak_out_pct_mcc":0.000469},{"rank_by_duration":75,"event_id":"51630_20160503T213000","start_time_utc":"2016-05-03T21:30:00","end_time_utc":"2016-05-04T07:45:00","year":2016,"duration_hours":10.25,"n_snapshots":41,"min_customers_out":1,"max_customers_out":35,"mean_customers_out":10.683,"peak_out_pct_mcc":0.002343},{"rank_by_duration":76,"event_id":"51630_20151027T143000","start_time_utc":"2015-10-27T14:30:00","end_time_utc":"2015-10-28T00:45:00","year":2015,"duration_hours":10.25,"n_snapshots":41,"min_customers_out":5,"max_customers_out":5,"mean_customers_out":5.0,"peak_out_pct_mcc":0.000335},{"rank_by_duration":77,"event_id":"51630_20190912T011500","start_time_utc":"2019-09-12T01:15:00","end_time_utc":"2019-09-12T11:15:00","year":2019,"duration_hours":10.0,"n_snapshots":40,"min_customers_out":25,"max_customers_out":41,"mean_customers_out":32.6,"peak_out_pct_mcc":0.002744},{"rank_by_duration":78,"event_id":"51630_20210817T203000","start_time_utc":"2021-08-17T20:30:00","end_time_utc":"2021-08-18T06:30:00","year":2021,"duration_hours":10.0,"n_snapshots":38,"min_customers_out":1,"max_customers_out":2,"mean_customers_out":1.289,"peak_out_pct_mcc":0.000134},{"rank_by_duration":79,"event_id":"51630_20151003T061500","start_time_utc":"2015-10-03T06:15:00","end_time_utc":"2015-10-03T16:15:00","year":2015,"duration_hours":10.0,"n_snapshots":40,"min_customers_out":1,"max_customers_out":2,"mean_customers_out":1.05,"peak_out_pct_mcc":0.000134},{"rank_by_duration":80,"event_id":"51630_20180622T204500","start_time_utc":"2018-06-22T20:45:00","end_time_utc":"2018-06-23T06:45:00","year":2018,"duration_hours":10.0,"n_snapshots":40,"min_customers_out":1,"max_customers_out":1,"mean_customers_out":1.0,"peak_out_pct_mcc":6.7e-05},{"rank_by_duration":81,"event_id":"51630_20210811T213000","start_time_utc":"2021-08-11T21:30:00","end_time_utc":"2021-08-12T07:15:00","year":2021,"duration_hours":9.75,"n_snapshots":39,"min_customers_out":6,"max_customers_out":1574,"mean_customers_out":426.923,"peak_out_pct_mcc":0.105362},{"rank_by_duration":82,"event_id":"51630_20221115T003000","start_time_utc":"2022-11-15T00:30:00","end_time_utc":"2022-11-15T10:15:00","year":2022,"duration_hours":9.75,"n_snapshots":39,"min_customers_out":8,"max_customers_out":119,"mean_customers_out":60.487,"peak_out_pct_mcc":0.007966},{"rank_by_duration":83,"event_id":"51630_20160514T194500","start_time_utc":"2016-05-14T19:45:00","end_time_utc":"2016-05-15T05:30:00","year":2016,"duration_hours":9.75,"n_snapshots":38,"min_customers_out":1,"max_customers_out":32,"mean_customers_out":8.342,"peak_out_pct_mcc":0.002142},{"rank_by_duration":84,"event_id":"51630_20230315T041500","start_time_utc":"2023-03-15T04:15:00","end_time_utc":"2023-03-15T14:00:00","year":2023,"duration_hours":9.75,"n_snapshots":39,"min_customers_out":12,"max_customers_out":19,"mean_customers_out":15.59,"peak_out_pct_mcc":0.001272},{"rank_by_duration":85,"event_id":"51630_20190428T223000","start_time_utc":"2019-04-28T22:30:00","end_time_utc":"2019-04-29T08:15:00","year":2019,"duration_hours":9.75,"n_snapshots":39,"min_customers_out":8,"max_customers_out":14,"mean_customers_out":10.769,"peak_out_pct_mcc":0.000937},{"rank_by_duration":86,"event_id":"51630_20250614T010000","start_time_utc":"2025-06-14T01:00:00","end_time_utc":"2025-06-14T10:45:00","year":2025,"duration_hours":9.75,"n_snapshots":39,"min_customers_out":2,"max_customers_out":5,"mean_customers_out":3.974,"peak_out_pct_mcc":0.000335},{"rank_by_duration":87,"event_id":"51630_20200327T233000","start_time_utc":"2020-03-27T23:30:00","end_time_utc":"2020-03-28T09:15:00","year":2020,"duration_hours":9.75,"n_snapshots":39,"min_customers_out":1,"max_customers_out":2,"mean_customers_out":1.333,"peak_out_pct_mcc":0.000134},{"rank_by_duration":88,"event_id":"51630_20180719T111500","start_time_utc":"2018-07-19T11:15:00","end_time_utc":"2018-07-19T21:00:00","year":2018,"duration_hours":9.75,"n_snapshots":39,"min_customers_out":1,"max_customers_out":1,"mean_customers_out":1.0,"peak_out_pct_mcc":6.7e-05},{"rank_by_duration":89,"event_id":"51630_20170729T234500","start_time_utc":"2017-07-29T23:45:00","end_time_utc":"2017-07-30T09:30:00","year":2017,"duration_hours":9.75,"n_snapshots":39,"min_customers_out":1,"max_customers_out":1,"mean_customers_out":1.0,"peak_out_pct_mcc":6.7e-05},{"rank_by_duration":90,"event_id":"51630_20221003T040000","start_time_utc":"2022-10-03T04:00:00","end_time_utc":"2022-10-03T13:30:00","year":2022,"duration_hours":9.5,"n_snapshots":38,"min_customers_out":8,"max_customers_out":585,"mean_customers_out":305.711,"peak_out_pct_mcc":0.039159},{"rank_by_duration":91,"event_id":"51630_20180816T041500","start_time_utc":"2018-08-16T04:15:00","end_time_utc":"2018-08-16T13:45:00","year":2018,"duration_hours":9.5,"n_snapshots":38,"min_customers_out":24,"max_customers_out":219,"mean_customers_out":85.868,"peak_out_pct_mcc":0.01466},{"rank_by_duration":92,"event_id":"51630_20190415T054500","start_time_utc":"2019-04-15T05:45:00","end_time_utc":"2019-04-15T15:15:00","year":2019,"duration_hours":9.5,"n_snapshots":38,"min_customers_out":6,"max_customers_out":190,"mean_customers_out":171.868,"peak_out_pct_mcc":0.012718},{"rank_by_duration":93,"event_id":"51630_20190108T040000","start_time_utc":"2019-01-08T04:00:00","end_time_utc":"2019-01-08T13:30:00","year":2019,"duration_hours":9.5,"n_snapshots":38,"min_customers_out":37,"max_customers_out":95,"mean_customers_out":75.158,"peak_out_pct_mcc":0.006359},{"rank_by_duration":94,"event_id":"51630_20200421T220000","start_time_utc":"2020-04-21T22:00:00","end_time_utc":"2020-04-22T07:30:00","year":2020,"duration_hours":9.5,"n_snapshots":38,"min_customers_out":7,"max_customers_out":45,"mean_customers_out":13.132,"peak_out_pct_mcc":0.003012},{"rank_by_duration":95,"event_id":"51630_20160225T060000","start_time_utc":"2016-02-25T06:00:00","end_time_utc":"2016-02-25T15:30:00","year":2016,"duration_hours":9.5,"n_snapshots":38,"min_customers_out":2,"max_customers_out":25,"mean_customers_out":9.158,"peak_out_pct_mcc":0.001673},{"rank_by_duration":96,"event_id":"51630_20250624T161500","start_time_utc":"2025-06-24T16:15:00","end_time_utc":"2025-06-25T01:45:00","year":2025,"duration_hours":9.5,"n_snapshots":38,"min_customers_out":4,"max_customers_out":4,"mean_customers_out":4.0,"peak_out_pct_mcc":0.000268},{"rank_by_duration":97,"event_id":"51630_20250310T140000","start_time_utc":"2025-03-10T14:00:00","end_time_utc":"2025-03-10T23:30:00","year":2025,"duration_hours":9.5,"n_snapshots":38,"min_customers_out":1,"max_customers_out":2,"mean_customers_out":1.026,"peak_out_pct_mcc":0.000134},{"rank_by_duration":98,"event_id":"51630_20250221T033000","start_time_utc":"2025-02-21T03:30:00","end_time_utc":"2025-02-21T13:00:00","year":2025,"duration_hours":9.5,"n_snapshots":38,"min_customers_out":1,"max_customers_out":2,"mean_customers_out":1.053,"peak_out_pct_mcc":0.000134},{"rank_by_duration":99,"event_id":"51630_20180518T221500","start_time_utc":"2018-05-18T22:15:00","end_time_utc":"2018-05-19T07:45:00","year":2018,"duration_hours":9.5,"n_snapshots":38,"min_customers_out":2,"max_customers_out":2,"mean_customers_out":2.0,"peak_out_pct_mcc":0.000134},{"rank_by_duration":100,"event_id":"51630_20190528T163000","start_time_utc":"2019-05-28T16:30:00","end_time_utc":"2019-05-29T02:00:00","year":2019,"duration_hours":9.5,"n_snapshots":38,"min_customers_out":1,"max_customers_out":1,"mean_customers_out":1.0,"peak_out_pct_mcc":6.7e-05},{"rank_by_duration":101,"event_id":"51630_20240320T210000","start_time_utc":"2024-03-20T21:00:00","end_time_utc":"2024-03-21T06:15:00","year":2024,"duration_hours":9.25,"n_snapshots":37,"min_customers_out":1,"max_customers_out":1744,"mean_customers_out":78.73,"peak_out_pct_mcc":0.116741},{"rank_by_duration":102,"event_id":"51630_20180523T060000","start_time_utc":"2018-05-23T06:00:00","end_time_utc":"2018-05-23T15:15:00","year":2018,"duration_hours":9.25,"n_snapshots":37,"min_customers_out":9,"max_customers_out":497,"mean_customers_out":113.649,"peak_out_pct_mcc":0.033269},{"rank_by_duration":103,"event_id":"51630_20250915T221500","start_time_utc":"2025-09-15T22:15:00","end_time_utc":"2025-09-16T07:30:00","year":2025,"duration_hours":9.25,"n_snapshots":37,"min_customers_out":339,"max_customers_out":449,"mean_customers_out":393.892,"peak_out_pct_mcc":0.030056},{"rank_by_duration":104,"event_id":"51630_20230622T034500","start_time_utc":"2023-06-22T03:45:00","end_time_utc":"2023-06-22T13:00:00","year":2023,"duration_hours":9.25,"n_snapshots":36,"min_customers_out":64,"max_customers_out":175,"mean_customers_out":94.222,"peak_out_pct_mcc":0.011714},{"rank_by_duration":105,"event_id":"51630_20250711T234500","start_time_utc":"2025-07-11T23:45:00","end_time_utc":"2025-07-12T09:00:00","year":2025,"duration_hours":9.25,"n_snapshots":37,"min_customers_out":32,"max_customers_out":32,"mean_customers_out":32.0,"peak_out_pct_mcc":0.002142},{"rank_by_duration":106,"event_id":"51630_20250723T081500","start_time_utc":"2025-07-23T08:15:00","end_time_utc":"2025-07-23T17:30:00","year":2025,"duration_hours":9.25,"n_snapshots":37,"min_customers_out":1,"max_customers_out":27,"mean_customers_out":4.703,"peak_out_pct_mcc":0.001807},{"rank_by_duration":107,"event_id":"51630_20240321T073000","start_time_utc":"2024-03-21T07:30:00","end_time_utc":"2024-03-21T16:45:00","year":2024,"duration_hours":9.25,"n_snapshots":36,"min_customers_out":1,"max_customers_out":7,"mean_customers_out":3.278,"peak_out_pct_mcc":0.000469},{"rank_by_duration":108,"event_id":"51630_20170810T131500","start_time_utc":"2017-08-10T13:15:00","end_time_utc":"2017-08-10T22:30:00","year":2017,"duration_hours":9.25,"n_snapshots":37,"min_customers_out":2,"max_customers_out":7,"mean_customers_out":3.054,"peak_out_pct_mcc":0.000469},{"rank_by_duration":109,"event_id":"51630_20240507T073000","start_time_utc":"2024-05-07T07:30:00","end_time_utc":"2024-05-07T16:45:00","year":2024,"duration_hours":9.25,"n_snapshots":37,"min_customers_out":1,"max_customers_out":1,"mean_customers_out":1.0,"peak_out_pct_mcc":6.7e-05},{"rank_by_duration":110,"event_id":"51630_20171020T221500","start_time_utc":"2017-10-20T22:15:00","end_time_utc":"2017-10-21T07:30:00","year":2017,"duration_hours":9.25,"n_snapshots":37,"min_customers_out":1,"max_customers_out":1,"mean_customers_out":1.0,"peak_out_pct_mcc":6.7e-05},{"rank_by_duration":111,"event_id":"51630_20151001T210000","start_time_utc":"2015-10-01T21:00:00","end_time_utc":"2015-10-02T06:00:00","year":2015,"duration_hours":9.0,"n_snapshots":36,"min_customers_out":23,"max_customers_out":3510,"mean_customers_out":507.306,"peak_out_pct_mcc":0.234955},{"rank_by_duration":112,"event_id":"51630_20181125T163000","start_time_utc":"2018-11-25T16:30:00","end_time_utc":"2018-11-26T01:30:00","year":2018,"duration_hours":9.0,"n_snapshots":36,"min_customers_out":11,"max_customers_out":256,"mean_customers_out":119.111,"peak_out_pct_mcc":0.017136},{"rank_by_duration":113,"event_id":"51630_20200708T021500","start_time_utc":"2020-07-08T02:15:00","end_time_utc":"2020-07-08T11:15:00","year":2020,"duration_hours":9.0,"n_snapshots":36,"min_customers_out":175,"max_customers_out":186,"mean_customers_out":182.333,"peak_out_pct_mcc":0.012451},{"rank_by_duration":114,"event_id":"51630_20250322T003000","start_time_utc":"2025-03-22T00:30:00","end_time_utc":"2025-03-22T09:30:00","year":2025,"duration_hours":9.0,"n_snapshots":36,"min_customers_out":6,"max_customers_out":38,"mean_customers_out":11.333,"peak_out_pct_mcc":0.002544},{"rank_by_duration":115,"event_id":"51630_20180308T111500","start_time_utc":"2018-03-08T11:15:00","end_time_utc":"2018-03-08T20:15:00","year":2018,"duration_hours":9.0,"n_snapshots":36,"min_customers_out":1,"max_customers_out":33,"mean_customers_out":4.444,"peak_out_pct_mcc":0.002209},{"rank_by_duration":116,"event_id":"51630_20181010T113000","start_time_utc":"2018-10-10T11:30:00","end_time_utc":"2018-10-10T20:30:00","year":2018,"duration_hours":9.0,"n_snapshots":36,"min_customers_out":10,"max_customers_out":11,"mean_customers_out":10.111,"peak_out_pct_mcc":0.000736},{"rank_by_duration":117,"event_id":"51630_20251116T183000","start_time_utc":"2025-11-16T18:30:00","end_time_utc":"2025-11-17T03:30:00","year":2025,"duration_hours":9.0,"n_snapshots":36,"min_customers_out":1,"max_customers_out":5,"mean_customers_out":1.333,"peak_out_pct_mcc":0.000335},{"rank_by_duration":118,"event_id":"51630_20190128T154500","start_time_utc":"2019-01-28T15:45:00","end_time_utc":"2019-01-29T00:45:00","year":2019,"duration_hours":9.0,"n_snapshots":36,"min_customers_out":1,"max_customers_out":1,"mean_customers_out":1.0,"peak_out_pct_mcc":6.7e-05},{"rank_by_duration":119,"event_id":"51630_20180210T091500","start_time_utc":"2018-02-10T09:15:00","end_time_utc":"2018-02-10T18:00:00","year":2018,"duration_hours":8.75,"n_snapshots":35,"min_customers_out":3,"max_customers_out":515,"mean_customers_out":368.8,"peak_out_pct_mcc":0.034474},{"rank_by_duration":120,"event_id":"51630_20211216T000000","start_time_utc":"2021-12-16T00:00:00","end_time_utc":"2021-12-16T08:45:00","year":2021,"duration_hours":8.75,"n_snapshots":35,"min_customers_out":1,"max_customers_out":109,"mean_customers_out":14.029,"peak_out_pct_mcc":0.007296},{"rank_by_duration":121,"event_id":"51630_20240627T121500","start_time_utc":"2024-06-27T12:15:00","end_time_utc":"2024-06-27T21:00:00","year":2024,"duration_hours":8.75,"n_snapshots":33,"min_customers_out":1,"max_customers_out":46,"mean_customers_out":21.848,"peak_out_pct_mcc":0.003079},{"rank_by_duration":122,"event_id":"51630_20210415T211500","start_time_utc":"2021-04-15T21:15:00","end_time_utc":"2021-04-16T06:00:00","year":2021,"duration_hours":8.75,"n_snapshots":35,"min_customers_out":1,"max_customers_out":1,"mean_customers_out":1.0,"peak_out_pct_mcc":6.7e-05},{"rank_by_duration":123,"event_id":"51630_20171003T010000","start_time_utc":"2017-10-03T01:00:00","end_time_utc":"2017-10-03T09:45:00","year":2017,"duration_hours":8.75,"n_snapshots":35,"min_customers_out":1,"max_customers_out":1,"mean_customers_out":1.0,"peak_out_pct_mcc":6.7e-05},{"rank_by_duration":124,"event_id":"51630_20220331T161500","start_time_utc":"2022-03-31T16:15:00","end_time_utc":"2022-04-01T00:45:00","year":2022,"duration_hours":8.5,"n_snapshots":32,"min_customers_out":6,"max_customers_out":240,"mean_customers_out":63.125,"peak_out_pct_mcc":0.016065},{"rank_by_duration":125,"event_id":"51630_20200810T144500","start_time_utc":"2020-08-10T14:45:00","end_time_utc":"2020-08-10T23:15:00","year":2020,"duration_hours":8.5,"n_snapshots":33,"min_customers_out":6,"max_customers_out":101,"mean_customers_out":31.636,"peak_out_pct_mcc":0.006761},{"rank_by_duration":126,"event_id":"51630_20250619T201500","start_time_utc":"2025-06-19T20:15:00","end_time_utc":"2025-06-20T04:45:00","year":2025,"duration_hours":8.5,"n_snapshots":34,"min_customers_out":1,"max_customers_out":44,"mean_customers_out":18.765,"peak_out_pct_mcc":0.002945},{"rank_by_duration":127,"event_id":"51630_20251227T141500","start_time_utc":"2025-12-27T14:15:00","end_time_utc":"2025-12-27T22:45:00","year":2025,"duration_hours":8.5,"n_snapshots":33,"min_customers_out":1,"max_customers_out":24,"mean_customers_out":15.879,"peak_out_pct_mcc":0.001607},{"rank_by_duration":128,"event_id":"51630_20180705T093000","start_time_utc":"2018-07-05T09:30:00","end_time_utc":"2018-07-05T18:00:00","year":2018,"duration_hours":8.5,"n_snapshots":34,"min_customers_out":15,"max_customers_out":17,"mean_customers_out":15.471,"peak_out_pct_mcc":0.001138},{"rank_by_duration":129,"event_id":"51630_20170625T003000","start_time_utc":"2017-06-25T00:30:00","end_time_utc":"2017-06-25T09:00:00","year":2017,"duration_hours":8.5,"n_snapshots":34,"min_customers_out":8,"max_customers_out":9,"mean_customers_out":8.618,"peak_out_pct_mcc":0.000602},{"rank_by_duration":130,"event_id":"51630_20230927T031500","start_time_utc":"2023-09-27T03:15:00","end_time_utc":"2023-09-27T11:45:00","year":2023,"duration_hours":8.5,"n_snapshots":34,"min_customers_out":1,"max_customers_out":4,"mean_customers_out":3.412,"peak_out_pct_mcc":0.000268},{"rank_by_duration":131,"event_id":"51630_20180403T194500","start_time_utc":"2018-04-03T19:45:00","end_time_utc":"2018-04-04T04:15:00","year":2018,"duration_hours":8.5,"n_snapshots":34,"min_customers_out":2,"max_customers_out":2,"mean_customers_out":2.0,"peak_out_pct_mcc":0.000134},{"rank_by_duration":132,"event_id":"51630_20230122T113000","start_time_utc":"2023-01-22T11:30:00","end_time_utc":"2023-01-22T20:00:00","year":2023,"duration_hours":8.5,"n_snapshots":34,"min_customers_out":1,"max_customers_out":1,"mean_customers_out":1.0,"peak_out_pct_mcc":6.7e-05},{"rank_by_duration":133,"event_id":"51630_20160903T191500","start_time_utc":"2016-09-03T19:15:00","end_time_utc":"2016-09-04T03:30:00","year":2016,"duration_hours":8.25,"n_snapshots":33,"min_customers_out":1,"max_customers_out":111,"mean_customers_out":37.515,"peak_out_pct_mcc":0.00743},{"rank_by_duration":134,"event_id":"51630_20211111T190000","start_time_utc":"2021-11-11T19:00:00","end_time_utc":"2021-11-12T03:15:00","year":2021,"duration_hours":8.25,"n_snapshots":33,"min_customers_out":15,"max_customers_out":38,"mean_customers_out":18.788,"peak_out_pct_mcc":0.002544},{"rank_by_duration":135,"event_id":"51630_20190310T161500","start_time_utc":"2019-03-10T16:15:00","end_time_utc":"2019-03-11T00:30:00","year":2019,"duration_hours":8.25,"n_snapshots":33,"min_customers_out":1,"max_customers_out":15,"mean_customers_out":12.455,"peak_out_pct_mcc":0.001004},{"rank_by_duration":136,"event_id":"51630_20230420T013000","start_time_utc":"2023-04-20T01:30:00","end_time_utc":"2023-04-20T09:45:00","year":2023,"duration_hours":8.25,"n_snapshots":33,"min_customers_out":3,"max_customers_out":3,"mean_customers_out":3.0,"peak_out_pct_mcc":0.000201},{"rank_by_duration":137,"event_id":"51630_20170225T231500","start_time_utc":"2017-02-25T23:15:00","end_time_utc":"2017-02-26T07:30:00","year":2017,"duration_hours":8.25,"n_snapshots":33,"min_customers_out":1,"max_customers_out":1,"mean_customers_out":1.0,"peak_out_pct_mcc":6.7e-05},{"rank_by_duration":138,"event_id":"51630_20191020T130000","start_time_utc":"2019-10-20T13:00:00","end_time_utc":"2019-10-20T21:00:00","year":2019,"duration_hours":8.0,"n_snapshots":30,"min_customers_out":13,"max_customers_out":974,"mean_customers_out":204.567,"peak_out_pct_mcc":0.065198},{"rank_by_duration":139,"event_id":"51630_20180906T014500","start_time_utc":"2018-09-06T01:45:00","end_time_utc":"2018-09-06T09:45:00","year":2018,"duration_hours":8.0,"n_snapshots":32,"min_customers_out":66,"max_customers_out":339,"mean_customers_out":202.5,"peak_out_pct_mcc":0.022692},{"rank_by_duration":140,"event_id":"51630_20150602T111500","start_time_utc":"2015-06-02T11:15:00","end_time_utc":"2015-06-02T19:15:00","year":2015,"duration_hours":8.0,"n_snapshots":30,"min_customers_out":1,"max_customers_out":41,"mean_customers_out":12.533,"peak_out_pct_mcc":0.002744},{"rank_by_duration":141,"event_id":"51630_20170908T121500","start_time_utc":"2017-09-08T12:15:00","end_time_utc":"2017-09-08T20:15:00","year":2017,"duration_hours":8.0,"n_snapshots":32,"min_customers_out":1,"max_customers_out":20,"mean_customers_out":7.594,"peak_out_pct_mcc":0.001339},{"rank_by_duration":142,"event_id":"51630_20190523T211500","start_time_utc":"2019-05-23T21:15:00","end_time_utc":"2019-05-24T05:15:00","year":2019,"duration_hours":8.0,"n_snapshots":32,"min_customers_out":2,"max_customers_out":17,"mean_customers_out":7.281,"peak_out_pct_mcc":0.001138},{"rank_by_duration":143,"event_id":"51630_20231215T023000","start_time_utc":"2023-12-15T02:30:00","end_time_utc":"2023-12-15T10:30:00","year":2023,"duration_hours":8.0,"n_snapshots":32,"min_customers_out":1,"max_customers_out":8,"mean_customers_out":2.094,"peak_out_pct_mcc":0.000536},{"rank_by_duration":144,"event_id":"51630_20180801T160000","start_time_utc":"2018-08-01T16:00:00","end_time_utc":"2018-08-02T00:00:00","year":2018,"duration_hours":8.0,"n_snapshots":32,"min_customers_out":1,"max_customers_out":2,"mean_customers_out":1.406,"peak_out_pct_mcc":0.000134},{"rank_by_duration":145,"event_id":"51630_20200826T161500","start_time_utc":"2020-08-26T16:15:00","end_time_utc":"2020-08-27T00:00:00","year":2020,"duration_hours":7.75,"n_snapshots":31,"min_customers_out":1,"max_customers_out":1969,"mean_customers_out":182.871,"peak_out_pct_mcc":0.131803},{"rank_by_duration":146,"event_id":"51630_20210727T014500","start_time_utc":"2021-07-27T01:45:00","end_time_utc":"2021-07-27T09:30:00","year":2021,"duration_hours":7.75,"n_snapshots":31,"min_customers_out":8,"max_customers_out":1688,"mean_customers_out":235.355,"peak_out_pct_mcc":0.112993},{"rank_by_duration":147,"event_id":"51630_20200121T223000","start_time_utc":"2020-01-21T22:30:00","end_time_utc":"2020-01-22T06:15:00","year":2020,"duration_hours":7.75,"n_snapshots":31,"min_customers_out":2,"max_customers_out":298,"mean_customers_out":173.871,"peak_out_pct_mcc":0.019948},{"rank_by_duration":148,"event_id":"51630_20180413T214500","start_time_utc":"2018-04-13T21:45:00","end_time_utc":"2018-04-14T05:30:00","year":2018,"duration_hours":7.75,"n_snapshots":31,"min_customers_out":4,"max_customers_out":122,"mean_customers_out":42.258,"peak_out_pct_mcc":0.008167},{"rank_by_duration":149,"event_id":"51630_20200827T140000","start_time_utc":"2020-08-27T14:00:00","end_time_utc":"2020-08-27T21:45:00","year":2020,"duration_hours":7.75,"n_snapshots":31,"min_customers_out":1,"max_customers_out":117,"mean_customers_out":9.71,"peak_out_pct_mcc":0.007832},{"rank_by_duration":150,"event_id":"51630_20160319T201500","start_time_utc":"2016-03-19T20:15:00","end_time_utc":"2016-03-20T04:00:00","year":2016,"duration_hours":7.75,"n_snapshots":31,"min_customers_out":14,"max_customers_out":73,"mean_customers_out":18.0,"peak_out_pct_mcc":0.004887},{"rank_by_duration":151,"event_id":"51630_20190912T181500","start_time_utc":"2019-09-12T18:15:00","end_time_utc":"2019-09-13T02:00:00","year":2019,"duration_hours":7.75,"n_snapshots":31,"min_customers_out":11,"max_customers_out":41,"mean_customers_out":16.097,"peak_out_pct_mcc":0.002744},{"rank_by_duration":152,"event_id":"51630_20250403T140000","start_time_utc":"2025-04-03T14:00:00","end_time_utc":"2025-04-03T21:45:00","year":2025,"duration_hours":7.75,"n_snapshots":31,"min_customers_out":19,"max_customers_out":19,"mean_customers_out":19.0,"peak_out_pct_mcc":0.001272},{"rank_by_duration":153,"event_id":"51630_20230928T130000","start_time_utc":"2023-09-28T13:00:00","end_time_utc":"2023-09-28T20:45:00","year":2023,"duration_hours":7.75,"n_snapshots":31,"min_customers_out":4,"max_customers_out":17,"mean_customers_out":12.387,"peak_out_pct_mcc":0.001138},{"rank_by_duration":154,"event_id":"51630_20240522T211500","start_time_utc":"2024-05-22T21:15:00","end_time_utc":"2024-05-23T05:00:00","year":2024,"duration_hours":7.75,"n_snapshots":29,"min_customers_out":14,"max_customers_out":14,"mean_customers_out":14.0,"peak_out_pct_mcc":0.000937},{"rank_by_duration":155,"event_id":"51630_20171025T130000","start_time_utc":"2017-10-25T13:00:00","end_time_utc":"2017-10-25T20:45:00","year":2017,"duration_hours":7.75,"n_snapshots":31,"min_customers_out":5,"max_customers_out":12,"mean_customers_out":8.742,"peak_out_pct_mcc":0.000803},{"rank_by_duration":156,"event_id":"51630_20191124T174500","start_time_utc":"2019-11-24T17:45:00","end_time_utc":"2019-11-25T01:30:00","year":2019,"duration_hours":7.75,"n_snapshots":31,"min_customers_out":1,"max_customers_out":10,"mean_customers_out":1.29,"peak_out_pct_mcc":0.000669},{"rank_by_duration":157,"event_id":"51630_20190325T140000","start_time_utc":"2019-03-25T14:00:00","end_time_utc":"2019-03-25T21:45:00","year":2019,"duration_hours":7.75,"n_snapshots":31,"min_customers_out":1,"max_customers_out":7,"mean_customers_out":3.161,"peak_out_pct_mcc":0.000469},{"rank_by_duration":158,"event_id":"51630_20181119T181500","start_time_utc":"2018-11-19T18:15:00","end_time_utc":"2018-11-20T02:00:00","year":2018,"duration_hours":7.75,"n_snapshots":29,"min_customers_out":1,"max_customers_out":3,"mean_customers_out":2.034,"peak_out_pct_mcc":0.000201},{"rank_by_duration":159,"event_id":"51630_20230405T094500","start_time_utc":"2023-04-05T09:45:00","end_time_utc":"2023-04-05T17:30:00","year":2023,"duration_hours":7.75,"n_snapshots":30,"min_customers_out":1,"max_customers_out":2,"mean_customers_out":1.1,"peak_out_pct_mcc":0.000134},{"rank_by_duration":160,"event_id":"51630_20150706T180000","start_time_utc":"2015-07-06T18:00:00","end_time_utc":"2015-07-07T01:45:00","year":2015,"duration_hours":7.75,"n_snapshots":29,"min_customers_out":1,"max_customers_out":2,"mean_customers_out":1.069,"peak_out_pct_mcc":0.000134},{"rank_by_duration":161,"event_id":"51630_20210430T203000","start_time_utc":"2021-04-30T20:30:00","end_time_utc":"2021-05-01T04:00:00","year":2021,"duration_hours":7.5,"n_snapshots":30,"min_customers_out":1,"max_customers_out":1040,"mean_customers_out":195.4,"peak_out_pct_mcc":0.069616},{"rank_by_duration":162,"event_id":"51630_20240210T093000","start_time_utc":"2024-02-10T09:30:00","end_time_utc":"2024-02-10T17:00:00","year":2024,"duration_hours":7.5,"n_snapshots":30,"min_customers_out":66,"max_customers_out":316,"mean_customers_out":166.0,"peak_out_pct_mcc":0.021153},{"rank_by_duration":163,"event_id":"51630_20171127T083000","start_time_utc":"2017-11-27T08:30:00","end_time_utc":"2017-11-27T16:00:00","year":2017,"duration_hours":7.5,"n_snapshots":30,"min_customers_out":39,"max_customers_out":204,"mean_customers_out":153.367,"peak_out_pct_mcc":0.013656},{"rank_by_duration":164,"event_id":"51630_20170721T131500","start_time_utc":"2017-07-21T13:15:00","end_time_utc":"2017-07-21T20:45:00","year":2017,"duration_hours":7.5,"n_snapshots":28,"min_customers_out":1,"max_customers_out":97,"mean_customers_out":46.786,"peak_out_pct_mcc":0.006493},{"rank_by_duration":165,"event_id":"51630_20230515T073000","start_time_utc":"2023-05-15T07:30:00","end_time_utc":"2023-05-15T15:00:00","year":2023,"duration_hours":7.5,"n_snapshots":30,"min_customers_out":72,"max_customers_out":86,"mean_customers_out":81.1,"peak_out_pct_mcc":0.005757},{"rank_by_duration":166,"event_id":"51630_20190718T151500","start_time_utc":"2019-07-18T15:15:00","end_time_utc":"2019-07-18T22:45:00","year":2019,"duration_hours":7.5,"n_snapshots":30,"min_customers_out":81,"max_customers_out":82,"mean_customers_out":81.033,"peak_out_pct_mcc":0.005489},{"rank_by_duration":167,"event_id":"51630_20160104T220000","start_time_utc":"2016-01-04T22:00:00","end_time_utc":"2016-01-05T05:30:00","year":2016,"duration_hours":7.5,"n_snapshots":30,"min_customers_out":6,"max_customers_out":41,"mean_customers_out":16.033,"peak_out_pct_mcc":0.002744},{"rank_by_duration":168,"event_id":"51630_20161009T153000","start_time_utc":"2016-10-09T15:30:00","end_time_utc":"2016-10-09T23:00:00","year":2016,"duration_hours":7.5,"n_snapshots":30,"min_customers_out":2,"max_customers_out":14,"mean_customers_out":10.733,"peak_out_pct_mcc":0.000937},{"rank_by_duration":169,"event_id":"51630_20151124T023000","start_time_utc":"2015-11-24T02:30:00","end_time_utc":"2015-11-24T10:00:00","year":2015,"duration_hours":7.5,"n_snapshots":30,"min_customers_out":1,"max_customers_out":8,"mean_customers_out":1.933,"peak_out_pct_mcc":0.000536},{"rank_by_duration":170,"event_id":"51630_20150511T224500","start_time_utc":"2015-05-11T22:45:00","end_time_utc":"2015-05-12T06:15:00","year":2015,"duration_hours":7.5,"n_snapshots":29,"min_customers_out":1,"max_customers_out":2,"mean_customers_out":1.034,"peak_out_pct_mcc":0.000134},{"rank_by_duration":171,"event_id":"51630_20231231T201500","start_time_utc":"2023-12-31T20:15:00","end_time_utc":"2024-01-01T03:45:00","year":2023,"duration_hours":7.5,"n_snapshots":30,"min_customers_out":1,"max_customers_out":1,"mean_customers_out":1.0,"peak_out_pct_mcc":6.7e-05},{"rank_by_duration":172,"event_id":"51630_20220330T134500","start_time_utc":"2022-03-30T13:45:00","end_time_utc":"2022-03-30T21:15:00","year":2022,"duration_hours":7.5,"n_snapshots":30,"min_customers_out":1,"max_customers_out":1,"mean_customers_out":1.0,"peak_out_pct_mcc":6.7e-05},{"rank_by_duration":173,"event_id":"51630_20210927T204500","start_time_utc":"2021-09-27T20:45:00","end_time_utc":"2021-09-28T04:15:00","year":2021,"duration_hours":7.5,"n_snapshots":30,"min_customers_out":1,"max_customers_out":1,"mean_customers_out":1.0,"peak_out_pct_mcc":6.7e-05},{"rank_by_duration":174,"event_id":"51630_20200515T024500","start_time_utc":"2020-05-15T02:45:00","end_time_utc":"2020-05-15T10:15:00","year":2020,"duration_hours":7.5,"n_snapshots":30,"min_customers_out":1,"max_customers_out":1,"mean_customers_out":1.0,"peak_out_pct_mcc":6.7e-05},{"rank_by_duration":175,"event_id":"51630_20191113T021500","start_time_utc":"2019-11-13T02:15:00","end_time_utc":"2019-11-13T09:45:00","year":2019,"duration_hours":7.5,"n_snapshots":30,"min_customers_out":1,"max_customers_out":1,"mean_customers_out":1.0,"peak_out_pct_mcc":6.7e-05},{"rank_by_duration":176,"event_id":"51630_20151027T023000","start_time_utc":"2015-10-27T02:30:00","end_time_utc":"2015-10-27T10:00:00","year":2015,"duration_hours":7.5,"n_snapshots":30,"min_customers_out":1,"max_customers_out":1,"mean_customers_out":1.0,"peak_out_pct_mcc":6.7e-05},{"rank_by_duration":177,"event_id":"51630_20190802T090000","start_time_utc":"2019-08-02T09:00:00","end_time_utc":"2019-08-02T16:15:00","year":2019,"duration_hours":7.25,"n_snapshots":28,"min_customers_out":10,"max_customers_out":142,"mean_customers_out":72.107,"peak_out_pct_mcc":0.009505},{"rank_by_duration":178,"event_id":"51630_20161202T130000","start_time_utc":"2016-12-02T13:00:00","end_time_utc":"2016-12-02T20:15:00","year":2016,"duration_hours":7.25,"n_snapshots":29,"min_customers_out":18,"max_customers_out":113,"mean_customers_out":58.034,"peak_out_pct_mcc":0.007564},{"rank_by_duration":179,"event_id":"51630_20221022T160000","start_time_utc":"2022-10-22T16:00:00","end_time_utc":"2022-10-22T23:15:00","year":2022,"duration_hours":7.25,"n_snapshots":29,"min_customers_out":1,"max_customers_out":22,"mean_customers_out":1.724,"peak_out_pct_mcc":0.001473},{"rank_by_duration":180,"event_id":"51630_20160728T110000","start_time_utc":"2016-07-28T11:00:00","end_time_utc":"2016-07-28T18:15:00","year":2016,"duration_hours":7.25,"n_snapshots":29,"min_customers_out":1,"max_customers_out":21,"mean_customers_out":11.276,"peak_out_pct_mcc":0.001406},{"rank_by_duration":181,"event_id":"51630_20160629T110000","start_time_utc":"2016-06-29T11:00:00","end_time_utc":"2016-06-29T18:15:00","year":2016,"duration_hours":7.25,"n_snapshots":29,"min_customers_out":2,"max_customers_out":21,"mean_customers_out":4.138,"peak_out_pct_mcc":0.001406},{"rank_by_duration":182,"event_id":"51630_20230815T200000","start_time_utc":"2023-08-15T20:00:00","end_time_utc":"2023-08-16T03:15:00","year":2023,"duration_hours":7.25,"n_snapshots":29,"min_customers_out":13,"max_customers_out":17,"mean_customers_out":14.345,"peak_out_pct_mcc":0.001138},{"rank_by_duration":183,"event_id":"51630_20240709T151500","start_time_utc":"2024-07-09T15:15:00","end_time_utc":"2024-07-09T22:30:00","year":2024,"duration_hours":7.25,"n_snapshots":29,"min_customers_out":1,"max_customers_out":8,"mean_customers_out":2.103,"peak_out_pct_mcc":0.000536},{"rank_by_duration":184,"event_id":"51630_20190617T183000","start_time_utc":"2019-06-17T18:30:00","end_time_utc":"2019-06-18T01:45:00","year":2019,"duration_hours":7.25,"n_snapshots":29,"min_customers_out":2,"max_customers_out":7,"mean_customers_out":4.069,"peak_out_pct_mcc":0.000469},{"rank_by_duration":185,"event_id":"51630_20190112T224500","start_time_utc":"2019-01-12T22:45:00","end_time_utc":"2019-01-13T06:00:00","year":2019,"duration_hours":7.25,"n_snapshots":29,"min_customers_out":4,"max_customers_out":7,"mean_customers_out":6.172,"peak_out_pct_mcc":0.000469},{"rank_by_duration":186,"event_id":"51630_20230822T004500","start_time_utc":"2023-08-22T00:45:00","end_time_utc":"2023-08-22T08:00:00","year":2023,"duration_hours":7.25,"n_snapshots":29,"min_customers_out":2,"max_customers_out":2,"mean_customers_out":2.0,"peak_out_pct_mcc":0.000134},{"rank_by_duration":187,"event_id":"51630_20180227T123000","start_time_utc":"2018-02-27T12:30:00","end_time_utc":"2018-02-27T19:45:00","year":2018,"duration_hours":7.25,"n_snapshots":29,"min_customers_out":1,"max_customers_out":2,"mean_customers_out":1.034,"peak_out_pct_mcc":0.000134},{"rank_by_duration":188,"event_id":"51630_20180627T143000","start_time_utc":"2018-06-27T14:30:00","end_time_utc":"2018-06-27T21:45:00","year":2018,"duration_hours":7.25,"n_snapshots":27,"min_customers_out":1,"max_customers_out":1,"mean_customers_out":1.0,"peak_out_pct_mcc":6.7e-05},{"rank_by_duration":189,"event_id":"51630_20180730T204500","start_time_utc":"2018-07-30T20:45:00","end_time_utc":"2018-07-31T03:45:00","year":2018,"duration_hours":7.0,"n_snapshots":28,"min_customers_out":1,"max_customers_out":975,"mean_customers_out":469.036,"peak_out_pct_mcc":0.065265},{"rank_by_duration":190,"event_id":"51630_20190424T223000","start_time_utc":"2019-04-24T22:30:00","end_time_utc":"2019-04-25T05:30:00","year":2019,"duration_hours":7.0,"n_snapshots":28,"min_customers_out":18,"max_customers_out":168,"mean_customers_out":70.821,"peak_out_pct_mcc":0.011246},{"rank_by_duration":191,"event_id":"51630_20150611T130000","start_time_utc":"2015-06-11T13:00:00","end_time_utc":"2015-06-11T20:00:00","year":2015,"duration_hours":7.0,"n_snapshots":28,"min_customers_out":8,"max_customers_out":160,"mean_customers_out":70.286,"peak_out_pct_mcc":0.01071},{"rank_by_duration":192,"event_id":"51630_20241025T024500","start_time_utc":"2024-10-25T02:45:00","end_time_utc":"2024-10-25T09:45:00","year":2024,"duration_hours":7.0,"n_snapshots":28,"min_customers_out":133,"max_customers_out":133,"mean_customers_out":133.0,"peak_out_pct_mcc":0.008903},{"rank_by_duration":193,"event_id":"51630_20201127T160000","start_time_utc":"2020-11-27T16:00:00","end_time_utc":"2020-11-27T23:00:00","year":2020,"duration_hours":7.0,"n_snapshots":28,"min_customers_out":24,"max_customers_out":122,"mean_customers_out":69.5,"peak_out_pct_mcc":0.008167},{"rank_by_duration":194,"event_id":"51630_20160729T044500","start_time_utc":"2016-07-29T04:45:00","end_time_utc":"2016-07-29T11:45:00","year":2016,"duration_hours":7.0,"n_snapshots":28,"min_customers_out":1,"max_customers_out":117,"mean_customers_out":95.929,"peak_out_pct_mcc":0.007832},{"rank_by_duration":195,"event_id":"51630_20180521T021500","start_time_utc":"2018-05-21T02:15:00","end_time_utc":"2018-05-21T09:15:00","year":2018,"duration_hours":7.0,"n_snapshots":28,"min_customers_out":105,"max_customers_out":105,"mean_customers_out":105.0,"peak_out_pct_mcc":0.007029},{"rank_by_duration":196,"event_id":"51630_20230722T203000","start_time_utc":"2023-07-22T20:30:00","end_time_utc":"2023-07-23T03:30:00","year":2023,"duration_hours":7.0,"n_snapshots":28,"min_customers_out":76,"max_customers_out":76,"mean_customers_out":76.0,"peak_out_pct_mcc":0.005087},{"rank_by_duration":197,"event_id":"51630_20211027T133000","start_time_utc":"2021-10-27T13:30:00","end_time_utc":"2021-10-27T20:30:00","year":2021,"duration_hours":7.0,"n_snapshots":27,"min_customers_out":19,"max_customers_out":38,"mean_customers_out":19.704,"peak_out_pct_mcc":0.002544},{"rank_by_duration":198,"event_id":"51630_20231220T131500","start_time_utc":"2023-12-20T13:15:00","end_time_utc":"2023-12-20T20:15:00","year":2023,"duration_hours":7.0,"n_snapshots":28,"min_customers_out":5,"max_customers_out":17,"mean_customers_out":9.786,"peak_out_pct_mcc":0.001138},{"rank_by_duration":199,"event_id":"51630_20151216T033000","start_time_utc":"2015-12-16T03:30:00","end_time_utc":"2015-12-16T10:30:00","year":2015,"duration_hours":7.0,"n_snapshots":28,"min_customers_out":16,"max_customers_out":16,"mean_customers_out":16.0,"peak_out_pct_mcc":0.001071},{"rank_by_duration":200,"event_id":"51630_20170604T104500","start_time_utc":"2017-06-04T10:45:00","end_time_utc":"2017-06-04T17:45:00","year":2017,"duration_hours":7.0,"n_snapshots":28,"min_customers_out":1,"max_customers_out":10,"mean_customers_out":1.321,"peak_out_pct_mcc":0.000669}]}